Workbook

Sheet Executive Dashboard
A1: AGI ERP DIGITIZATION CONTROL TOWER
A2: Evidence-based enterprise transformation baseline — project completion is not treated as process maturity
A3: As of 14 Sep 2026 | Current evidence position: five calibration design packs complete; O2C provisionally reviewed as S1–S2 / E2 Candidate; no wave yet verified with E3+ production execution evidence.
A5: CALIBRATION WAVES DESIGNED | D5: PROVISIONAL EVIDENCE REVIEWS | G5: LIVE-CALIBRATED WAVES (E3+) | J5: O2C PILOT KPIs | M5: O2C EVENT SCHEMA FIELDS
A6: =COUNTA('Calibration Waves'!B2:B6) -> 5 | D6: =COUNTIF('Calibration Waves'!F2:F6,"*provisional evidence calibration completed*") -> 1 | G6: 0 | J6: =COUNTA('O2C Pilot KPI Baseline'!A2:A16) -> 15 | M6: =COUNTA('O2C Event Schema'!A2:A34) -> 33
A7: 5 / 5 design packs complete | D7: Wave 1 O2C only | G7: Production extraction has not started | J7: Baseline values remain pending | M7: 33-field canonical event schema + 59 normalized O2C activities
A10: TRANSFORMATION CALIBRATION PIPELINE
A11: 1. Process Registry / Taxonomy | D11: 2. Calibration Design Packs | G11: 3. Provisional Evidence Review | J11: 4. Live E3 Calibration | M11: 5. Verified E4/E5 Outcomes
A12: COMPLETE | D12: 5 / 5 COMPLETE | G12: 1 / 5 COMPLETE | J12: 0 / 5 | M12: 0 / 5
A13: Enterprise L0-L6 taxonomy and process registry established | D13: O2C, S2P, D2POD, A2P and P2P packs complete | G13: O2C evidence review completed provisionally | J13: Requires production event extraction | M13: Requires measured baseline and verified business value
A15: DEPARTMENTAL TRANSFORMATION PORTFOLIO
A16: # | B16: Functional Wing | D16: Journey | F16: Design Pack | H16: Evidence Review | J16: Live Calibration | L16: Current State / Evidence | N16: Next Action
A17: 1 | B17: ='Dashboard Inputs'!A2 -> Sales | D17: ='Dashboard Inputs'!B2 -> Order-to-Cash | F17: ='Dashboard Inputs'!D2 -> Complete | H17: ='Dashboard Inputs'!E2 -> Complete | J17: ='Dashboard Inputs'!F2 -> Pending | L17: ='Dashboard Inputs'!G2&" / "&'Dashboard Inputs'!H2 -> S1-S2 (provisional) / E2 Candidate | N17: ='Dashboard Inputs'!K2 -> Treat AOPL only as the provisional first-to-check. Issue its P0 requests DR-O2C-01/02/03/04/07/09/10, verify the latest complete 30-day Sales Eco→BC→Logistics→Finance chain, and select a pilot only after all 7 mandatory gates pass; if AOPL fails a gate, validate AGL next.
A18: 2 | B18: ='Dashboard Inputs'!A3 -> SCM | D18: ='Dashboard Inputs'!B3 -> Source-to-Pay | F18: ='Dashboard Inputs'!D3 -> Complete | H18: ='Dashboard Inputs'!E3 -> Pending | J18: ='Dashboard Inputs'!F3 -> Pending | L18: ='Dashboard Inputs'!G3&" / "&'Dashboard Inputs'!H3 -> Not calibrated / E1-E2 Design Evidence | N18: ='Dashboard Inputs'!K3 -> Run evidence review and extract demand→vendor→RFQ→PO→GRN/QC→invoice→payment events once live evidence is available.
A19: 3 | B19: ='Dashboard Inputs'!A4 -> Logistics | D19: ='Dashboard Inputs'!B4 -> Delivery-to-POD | F19: ='Dashboard Inputs'!D4 -> Complete | H19: ='Dashboard Inputs'!E4 -> Pending | J19: ='Dashboard Inputs'!F4 -> Pending | L19: ='Dashboard Inputs'!G4&" / "&'Dashboard Inputs'!H4 -> Not calibrated / E1-E2 Design Evidence | N19: ='Dashboard Inputs'!K4 -> Validate actual digital coverage from DO readiness through POD and reconciliation using live trip/dispatch events.
A20: 4 | B20: ='Dashboard Inputs'!A5 -> HR | D20: ='Dashboard Inputs'!B5 -> Attendance-to-Payroll | F20: ='Dashboard Inputs'!D5 -> Complete | H20: ='Dashboard Inputs'!E5 -> Pending | J20: ='Dashboard Inputs'!F5 -> Pending | L20: ='Dashboard Inputs'!G5&" / "&'Dashboard Inputs'!H5 -> Not calibrated / E1 Design Evidence | N20: ='Dashboard Inputs'!K5 -> Validate master data, attendance-device flow, payroll run, bank response and payroll→BC posting using consecutive payroll periods.
A21: 5 | B21: ='Dashboard Inputs'!A6 -> Production | D21: ='Dashboard Inputs'!B6 -> Plan-to-Produce | F21: ='Dashboard Inputs'!D6 -> Complete | H21: ='Dashboard Inputs'!E6 -> Pending | J21: ='Dashboard Inputs'!F6 -> Pending | L21: ='Dashboard Inputs'!G6&" / "&'Dashboard Inputs'!H6 -> Not calibrated / E1 Design Evidence | N21: ='Dashboard Inputs'!K6 -> Sample production orders end-to-end, including materials, operation events, QC, FG, scrap/by-product and costing reconciliation.
A22: 6 | B22: ='Dashboard Inputs'!A7 -> Finance | D22: ='Dashboard Inputs'!B7 -> Record-to-Report | F22: ='Dashboard Inputs'!D7 -> Registry baseline | H22: ='Dashboard Inputs'!E7 -> Pending | J22: ='Dashboard Inputs'!F7 -> Pending | L22: ='Dashboard Inputs'!G7&" / "&'Dashboard Inputs'!H7 -> Not calibrated / E1 Design Evidence | N22: ='Dashboard Inputs'!K7 -> Create R2R calibration pack and sample actual close, reconciliation, posting and reporting evidence.
A23: 7 | B23: ='Dashboard Inputs'!A8 -> Quality Control | D23: ='Dashboard Inputs'!B8 -> Quality-to-Release | F23: ='Dashboard Inputs'!D8 -> Registry baseline | H23: ='Dashboard Inputs'!E8 -> Pending | J23: ='Dashboard Inputs'!F8 -> Pending | L23: ='Dashboard Inputs'!G8&" / "&'Dashboard Inputs'!H8 -> Not calibrated / E1 Composite Evidence | N23: ='Dashboard Inputs'!K8 -> Create standalone QC discovery/calibration pack and validate incoming, in-process and final inspection evidence.
A24: 8 | B24: ='Dashboard Inputs'!A9 -> Inventory / Warehouse | D24: ='Dashboard Inputs'!B9 -> Inventory-to-Fulfilment | F24: ='Dashboard Inputs'!D9 -> Registry baseline | H24: ='Dashboard Inputs'!E9 -> Pending | J24: ='Dashboard Inputs'!F9 -> Pending | L24: ='Dashboard Inputs'!G9&" / "&'Dashboard Inputs'!H9 -> Not calibrated / E1-E2 Candidate | N24: ='Dashboard Inputs'!K9 -> Create dedicated inventory calibration pack and validate stock accuracy, reservation, movement, cycle count and inventory→GL evidence.
A27: EXECUTIVE INSIGHTS
A28: Evidence discipline | E28: Current bottleneck | I28: Immediate action | M28: Next promotion gate
A29: Jira Done / configured capability supports E2 only. It does not prove execution, adoption or realized value. | E29: No unified production O2C event log yet, so cycle time, variants, STP and human dependency are not verified. | I29: Start Wave 1 event extraction across Sales Eco, Business Central and Logistics using the O2C Event Schema and Source-to-Field Mapping. | M29: E3 = real production cases; E4 = repeatable measured KPIs/variants; E5 = verified improvement against baseline.
I34: CONTROL TOWER STATUS
I35: Metric | K35: Current Position | M35: Implication
I36: Project status visibility | K36: Available | M36: ERP plan/Jira show delivery progress, not transformation maturity
I37: Process taxonomy | K37: Established | M37: Stable L0-L6 process identity now exists
I38: O2C evidence review | K38: Provisional E2 Candidate | M38: Ready for production event extraction
I39: Unified event log | K39: Not yet built | M39: Prevents verified cross-system KPI reporting
I40: Verified business outcomes | K40: Baseline pending | M40: No productivity, cycle-time or cost claim should be reported as realized yet
A42: O2C PILOT SBU SELECTION
A43: Current Position | D43: Provisional First-to-Check | G43: Selection Gate | J43: Why Not Selected Yet | M43: Immediate Next Action
A44: Pilot selection pending live data evidence | D44: AOPL — not selected | G44: 7/7 mandatory gates must pass | J44: Project-plan chronology and Jira/email activity do not prove end-to-end production lineage, adoption or reconciled source coverage. | M44: Issue P0 data requests and validate Sales Eco → BC → Logistics → Finance coverage before scoring candidates.

Sheet Dashboard Inputs
A1: Wing | B1: Journey | C1: Functional Wings | D1: Design Pack | E1: Provisional Evidence Review | F1: Live Calibration | G1: Provisional Current State | H1: Provisional Evidence Level | I1: Calibration Readiness | J1: Current Evidence Position | K1: Next Action | L1: Primary Owner(s) | M1: Primary Evidence Source | N1: Last Updated
A2: Sales | B2: Order-to-Cash | C2: Sales → Inventory → Logistics → Finance | D2: Complete | E2: Complete | F2: Pending | G2: S1-S2 (provisional) | H2: E2 Candidate | I2: High | J2: Implementation/QA stabilization evidence exists; production execution baseline is not yet verified. The 33-field event schema, 59-activity dictionary, source mapping, extraction runbook, data-request pack, 15 quality gates, evidence-gated SBU selection matrix and intake tracker are now prepared for Wave 1. | K2: Treat AOPL only as the provisional first-to-check. Issue its P0 requests DR-O2C-01/02/03/04/07/09/10, verify the latest complete 30-day Sales Eco→BC→Logistics→Finance chain, and select a pilot only after all 7 mandatory gates pass; if AOPL fails a gate, validate AGL next. | L2: Sales + Product + Finance + Logistics | M2: O2C Calibration Register; Source-to-Field Mapping; Extraction Runbook; Data Request Pack; Data Quality Gates; Pilot SBU Selection; Pilot Evidence Intake; BSES Jira | N2: 2026-09-15
A3: SCM | B3: Source-to-Pay | C3: SCM → Inventory/QC → Finance | D3: Complete | E3: Pending | F3: Pending | G3: Not calibrated | H3: E1-E2 Design Evidence | I3: Medium-High | J3: Detailed process catalogue and fit-gap/UAT evidence exist; actual production execution is not yet calibrated. | K3: Run evidence review and extract demand→vendor→RFQ→PO→GRN/QC→invoice→payment events once live evidence is available. | L3: SCM + ERP Team + Finance | M3: Signed SCM SDD; SCM BC annexes; S2P design pack | N3: 2026-09-14
A4: Logistics | B4: Delivery-to-POD | C4: Sales → Logistics → Inventory → Finance | D4: Complete | E4: Pending | F4: Pending | G4: Not calibrated | H4: E1-E2 Design Evidence | I4: Medium-High | J4: Detailed logistics target process exists, including loading, gate, dispatch, POD and exception handling; live telemetry is not yet verified. | K4: Validate actual digital coverage from DO readiness through POD and reconciliation using live trip/dispatch events. | L4: Logistics + ERP/Product + Warehouse | M4: Logistics PRD/SDD; D2POD design pack | N4: 2026-09-14
A5: HR | B5: Attendance-to-Payroll | C5: HR → Finance | D5: Complete | E5: Pending | F5: Pending | G5: Not calibrated | H5: E1 Design Evidence | I5: Medium-High | J5: HR scope, WBS, integrations and process requirements are defined; production attendance/payroll evidence has not been calibrated. | K5: Validate master data, attendance-device flow, payroll run, bank response and payroll→BC posting using consecutive payroll periods. | L5: HR + Payroll + Finance + ERP Team | M5: HR Module Project Management Annexes; A2P design pack | N5: 2026-09-14
A6: Production | B6: Plan-to-Produce | C6: Planning → Production → QC → Inventory → Finance | D6: Complete | E6: Pending | F6: Pending | G6: Not calibrated | H6: E1 Design Evidence | I6: Medium | J6: Production process and AIL variant are mapped, but shop-floor, QC, genealogy, instrumentation and costing evidence still require live validation. | K6: Sample production orders end-to-end, including materials, operation events, QC, FG, scrap/by-product and costing reconciliation. | L6: Production + QC + Inventory + Finance + ERP Team | M6: Production BRD/Data Record; P2P design pack | N6: 2026-09-14
A7: Finance | B7: Record-to-Report | C7: Finance / Accounting | D7: Registry baseline | E7: Pending | F7: Pending | G7: Not calibrated | H7: E1 Design Evidence | I7: Medium | J7: Finance SDD defines AP, AR, bank, FA, close and controls; no dedicated live R2R calibration wave has yet been run. | K7: Create R2R calibration pack and sample actual close, reconciliation, posting and reporting evidence. | L7: Finance + ERP Team | M7: 04.5 Accounts & Finance SDD; Process Registry | N7: 2026-09-14
A8: Quality Control | B8: Quality-to-Release | C8: QC → Production/Inventory | D8: Registry baseline | E8: Pending | F8: Pending | G8: Not calibrated | H8: E1 Composite Evidence | I8: Low-Medium | J8: QC requirements are evidenced through Production and SCM artefacts; standalone QC operating evidence is incomplete. | K8: Create standalone QC discovery/calibration pack and validate incoming, in-process and final inspection evidence. | L8: QC + Production + SCM + ERP Team | M8: Production/SCM quality requirements; Process Registry | N8: 2026-09-14
A9: Inventory / Warehouse | B9: Inventory-to-Fulfilment | C9: Inventory → Warehouse → Sales/Production/Logistics | D9: Registry baseline | E9: Pending | F9: Pending | G9: Not calibrated | H9: E1-E2 Candidate | I9: Medium | J9: Inventory design covers item/location/bin, receipts, transfers, picks, counts, costing and reconciliation; operational migration/reconciliation evidence remains incomplete. | K9: Create dedicated inventory calibration pack and validate stock accuracy, reservation, movement, cycle count and inventory→GL evidence. | L9: Inventory/Warehouse + Finance + ERP Team | M9: Inventory SDD; ERP plan/migration evidence; Process Registry | N9: 2026-09-14
A11: Calibration Stage | B11: Completed Waves | C11: Total Waves | D11: Completion %
A12: Design Packs Complete | B12: 5 | C12: 5 | D12: =B12/C12 -> 1
A13: Provisional Evidence Review | B13: 1 | C13: 5 | D13: =B13/C13 -> 0.2
A14: Live E3 Execution Calibration | B14: 0 | C14: 5 | D14: =B14/C14 -> 0
A15: Measured E4 Baseline | B15: 0 | C15: 5 | D15: =B15/C15 -> 0
A16: Outcome E5 Verification | B16: 0 | C16: 5 | D16: =B16/C16 -> 0

Sheet README
A1: AGI Enterprise Process Registry v1
A2: Purpose | B2: Create one evidence-based canonical process registry for management transformation visibility across ERP digitization, workflow automation, AI assistance and bounded agentic execution.
A3: Version | B3: v1 - 2026-09-14
A4: Scope | B4: Sales; Finance & Accounts; SCM / Procurement / Commercial; Inventory & Warehouse; Logistics; Production / Manufacturing; Quality Control; Human Resources.
A5: Important | B5: The registry is a taxonomy baseline. Current S-state and E-level fields are provisional until calibrated against production execution and outcome evidence.
A6: Core Rule 1 | B6: Use one canonical process with organization/SBU variants instead of duplicating the same process per company.
A7: Core Rule 2 | B7: Keep functional hierarchy (L0-L6) separate from horizontal end-to-end value streams.
A8: Core Rule 3 | B8: Transformation maturity should ultimately be measured at L5/L6 and rolled up to L3; L3 averages can hide human/manual decisions.
A9: Core Rule 4 | B9: S5 agentic autonomy is not a universal target. The right target depends on business value, control criticality, safety, legal constraints, data quality and reversibility.
A10: Core Rule 5 | B10: Do not infer current maturity from BRD/FRD/SDD completeness, configuration, or schedule progress alone.
A11: Registry Rows | B11: 94

Sheet Process Registry
A1: Process ID | B1: L0 Enterprise | C1: L1 Organization / SBU | D1: L2 Functional Wing | E1: L3 Process Group | F1: Representative L4 Sub-processes | G1: E2E Value Stream | H1: Current State (Provisional) | I1: Target State (Provisional) | J1: Evidence Level (Provisional) | K1: Calibration Status | L1: Management Note | M1: Source Title | N1: Source URL
A2: SAL-01 | B2: AGI | C2: Canonical / all applicable SBUs | D2: Sales | E2: Customer & Channel Management | F2: Customer onboarding; Customer Type; dealer/retailer/site relationship; lifecycle/status | G2: O2C | H2: Candidate S1-S2; calibration required | I2: S2 | J2: E2 | K2: Not calibrated | L2: Design/product/configuration evidence exists; require production usage/outcome evidence before E3/E4. | M2: Business Process Mapping Document - Primary Sales_UPDATED_SDD | N2: https://docs.google.com/document/d/1IoV-RaOxb83z2IttGlRKy863G_pckAGUegBqnRkemgc/edit?usp=drivesdk
A3: SAL-02 | B3: AGI | C3: Canonical / all applicable SBUs | D3: Sales | E3: Territory & Sales Organization Management | F3: Territory hierarchy; salesperson assignment; RC assignment; organization/user access | G3: O2C | H3: Candidate S1-S2; calibration required | I3: S2 | J3: E2 | K3: Not calibrated | L3: Design/product/configuration evidence exists; require production usage/outcome evidence before E3/E4. | M3: Business Process Mapping Document - Primary Sales_UPDATED_SDD | N3: https://docs.google.com/document/d/1IoV-RaOxb83z2IttGlRKy863G_pckAGUegBqnRkemgc/edit?usp=drivesdk
A4: SAL-03 | B4: AGI | C4: Canonical / all applicable SBUs | D4: Sales | E4: Lead, Site & Opportunity Management | F4: Site identification; influencer mapping; opportunity qualification; conversion/loss | G4: L2O | H4: Candidate S1-S2; calibration required | I4: S3 | J4: E2 | K4: Not calibrated | L4: Design/product/configuration evidence exists; require production usage/outcome evidence before E3/E4. | M4: Business Process Mapping Document - Primary Sales_UPDATED_SDD | N4: https://docs.google.com/document/d/1IoV-RaOxb83z2IttGlRKy863G_pckAGUegBqnRkemgc/edit?usp=drivesdk
A5: SAL-04 | B5: AGI | C5: Canonical / all applicable SBUs | D5: Sales | E5: Quotation Management | F5: Quote creation; pricing; validity; approval; conversion | G5: O2C | H5: Candidate S1-S2; calibration required | I5: S2 | J5: E2 | K5: Not calibrated | L5: Design/product/configuration evidence exists; require production usage/outcome evidence before E3/E4. | M5: Business Process Mapping Document - Primary Sales_UPDATED_SDD | N5: https://docs.google.com/document/d/1IoV-RaOxb83z2IttGlRKy863G_pckAGUegBqnRkemgc/edit?usp=drivesdk
A6: SAL-05 | B6: AGI | C6: Canonical / all applicable SBUs | D6: Sales | E6: Order Management | F6: Customer order; Sales Order creation; validation; approval/rejection/resubmission | G6: O2C | H6: Candidate S1-S2; calibration required | I6: S2 | J6: E2 | K6: Not calibrated | L6: Design/product/configuration evidence exists; require production usage/outcome evidence before E3/E4. | M6: Business Process Mapping Document - Primary Sales_UPDATED_SDD | N6: https://docs.google.com/document/d/1IoV-RaOxb83z2IttGlRKy863G_pckAGUegBqnRkemgc/edit?usp=drivesdk
A7: SAL-06 | B7: AGI | C7: Canonical / all applicable SBUs | D7: Sales | E7: Pricing, Discount & Commercial Control | F7: Price determination; discount; scheme; approval; exception | G7: O2C | H7: Candidate S1-S2; calibration required | I7: S2 | J7: E2 | K7: Not calibrated | L7: Design/product/configuration evidence exists; require production usage/outcome evidence before E3/E4. | M7: Business Process Mapping Document - Primary Sales_UPDATED_SDD | N7: https://docs.google.com/document/d/1IoV-RaOxb83z2IttGlRKy863G_pckAGUegBqnRkemgc/edit?usp=drivesdk
A8: SAL-07 | B8: AGI | C8: Canonical / all applicable SBUs | D8: Sales | E8: Credit Management | F8: Credit-limit check; RC-based credit; holds; override/escalation | G8: O2C | H8: Candidate S1-S2; calibration required | I8: S2 | J8: E2 | K8: Not calibrated | L8: Design/product/configuration evidence exists; require production usage/outcome evidence before E3/E4. | M8: Business Process Mapping Document - Primary Sales_UPDATED_SDD | N8: https://docs.google.com/document/d/1IoV-RaOxb83z2IttGlRKy863G_pckAGUegBqnRkemgc/edit?usp=drivesdk
A9: SAL-08 | B9: AGI | C9: Canonical / all applicable SBUs | D9: Sales | E9: Fulfilment Coordination | F9: DO initiation; DN status; partial delivery; substitution; outstanding balance | G9: O2C / I2F | H9: Candidate S1-S2; calibration required | I9: S2 | J9: E2 | K9: Not calibrated | L9: Design/product/configuration evidence exists; require production usage/outcome evidence before E3/E4. | M9: Business Process Mapping Document - Primary Sales_UPDATED_SDD | N9: https://docs.google.com/document/d/1IoV-RaOxb83z2IttGlRKy863G_pckAGUegBqnRkemgc/edit?usp=drivesdk
A10: SAL-09 | B10: AGI | C10: Canonical / all applicable SBUs | D10: Sales | E10: Billing & Invoice Coordination | F10: Invoice trigger; invoice reference; Sales Eco/BC status synchronization | G10: O2C | H10: Candidate S1-S2; calibration required | I10: S2 | J10: E2 | K10: Not calibrated | L10: Design/product/configuration evidence exists; require production usage/outcome evidence before E3/E4. | M10: Business Process Mapping Document - Primary Sales_UPDATED_SDD | N10: https://docs.google.com/document/d/1IoV-RaOxb83z2IttGlRKy863G_pckAGUegBqnRkemgc/edit?usp=drivesdk
A11: SAL-10 | B11: AGI | C11: Canonical / all applicable SBUs | D11: Sales | E11: Collection Management | F11: Money receipt; approval/rejection; ledger synchronization; reconciliation | G11: O2C | H11: Candidate S1-S2; calibration required | I11: S2 | J11: E2 | K11: Not calibrated | L11: Design/product/configuration evidence exists; require production usage/outcome evidence before E3/E4. | M11: Business Process Mapping Document - Primary Sales_UPDATED_SDD | N11: https://docs.google.com/document/d/1IoV-RaOxb83z2IttGlRKy863G_pckAGUegBqnRkemgc/edit?usp=drivesdk
A12: SAL-11 | B12: AGI | C12: Canonical / all applicable SBUs | D12: Sales | E12: Sales Return & Adjustment | F12: Return request; DN validation; approval; inventory/financial adjustment | G12: O2C | H12: Candidate S1-S2; calibration required | I12: S2 | J12: E2 | K12: Not calibrated | L12: Design/product/configuration evidence exists; require production usage/outcome evidence before E3/E4. | M12: Business Process Mapping Document - Primary Sales_UPDATED_SDD | N12: https://docs.google.com/document/d/1IoV-RaOxb83z2IttGlRKy863G_pckAGUegBqnRkemgc/edit?usp=drivesdk
... A95: HR-11 | B95: AGI | C95: Canonical / all applicable SBUs | D95: Human Resources | E95: Performance Management | F95: KPI/OKR; scorecard; competency; review | G95: P2PPL | H95: TBD | I95: S3 | J95: E1 | K95: Not calibrated | L95: Discovery/annex baseline exists; current partner build, production use and payroll execution need evidence. | M95: hr_module_project_management_annexes_2026-07-18 | N95: https://docs.google.com/spreadsheets/d/1XfHiOhLTJvGO_VKHyitZ8ijc_og8feRt5wAfyi8PC48/edit?usp=drivesdk

Sheet Hierarchy & Coding
A1: Level | B1: Definition | C1: Example | D1: Rule
A2: L0 | B2: Enterprise | C2: AGI | D2: Single enterprise identity.
A3: L1 | B3: Organization / SBU | C3: AIL / ACL / ACSL / AOPL / AGL | D3: Attach organization variants to canonical processes; do not duplicate taxonomy unnecessarily.
A4: L2 | B4: Functional Wing | C4: Sales | D4: Department / functional ownership view.
A5: L3 | B5: Process Group | C5: Order Management | D5: Stable canonical process group used for management aggregation.
A6: L4 | B6: Sub-process | C6: Sales Order Processing | D6: Functional decomposition of L3.
A7: L5 | B7: Activity | C7: Validate Sales Order | D7: Operational activity where human/system contribution can be measured.
A8: L6 | B8: Task / Decision | C8: Check customer, RC, price, credit, stock and approval | D8: Atomic task/decision for automation and control analysis.
A10: Dimension | B10: Definition | C10: Examples | D10: Rule
A11: E2E Value Stream | B11: Horizontal process journey spanning multiple wings | C11: O2C; S2P; P2P; Q2R; I2F; D2POD; R2R; H2R | D11: Use as a separate dimension rather than forcing an end-to-end journey into L3.
A12: Canonical process variant | B12: Same process across legal entities/SBUs | C12: AGI.SALES.ORDER.SALES_ORDER + AIL/ACL/AGL variants | D12: One canonical process, multiple organization-specific variants.

Sheet Transformation States
A1: State | B1: Name | C1: Definition | D1: Typical Human Role | E1: Important Guardrail
A2: S0 | B2: Manual / Fragmented | C2: Work is performed through paper, spreadsheets, email, phone, memory or disconnected tools. | D2: Performs most execution and decisions. | E2: Baseline only; identify control/data risks.
A3: S1 | B3: Digitized / System of Record | C3: Process is captured in an approved system with structured data and traceability. | D3: Executes process in system. | E3: Digitized does not mean automated or adopted.
A4: S2 | B4: Workflow / Rules Automated | C4: Deterministic validations, routing, calculations, integrations and approvals are automated. | D4: Handles exceptions and required approvals. | E4: Rules and SoD remain explicit.
A5: S3 | B5: AI-assisted / Copilot | C5: AI recommends, summarizes, predicts or detects anomalies while humans retain decision authority. | D5: Reviews/accepts/rejects AI output. | E5: Require evidence quality, explainability and human accountability.
A6: S4 | B6: Agent-operated with Human Approval / Supervision | C6: Agent performs multi-step execution but material decisions/actions require human approval or active supervision. | D6: Approves/supervises exceptions and high-impact actions. | E6: Use only where controls, observability and rollback are adequate.
A7: S5 | B7: Agentic / Autonomous within Guardrails | C7: Agent autonomously executes an approved bounded process and escalates exceptions. | D7: Defines guardrails and handles escalations. | E7: Not a universal target. Safety, financial, legal and control-critical processes may optimally stop at S2-S4.

Sheet Evidence Levels
A1: Level | B1: Name | C1: Minimum Evidence Standard | D1: Use in Management Reporting
A2: E0 | B2: No evidence | C2: Statement, assumption or undocumented claim only. | D2: Do not use as maturity fact.
A3: E1 | B3: Design evidence | C3: Approved BRD/FRD/SDD/process map/config specification. | D3: Shows intended design, not actual execution.
A4: E2 | B4: Build / configuration evidence | C4: Working build, configuration, test environment, UAT artifact, integration proof or prototype. | D4: Shows capability exists; adoption/production outcome not proven.
A5: E3 | B5: Production execution evidence | C5: Production transactions/logs demonstrate process is live and repeatedly executed. | D5: Eligible for verified current-state reporting.
A6: E4 | B6: Outcome / adoption evidence | C6: Usage/adoption metrics, cycle-time, exception, quality or productivity outcomes demonstrate operational value. | D6: Eligible for realized-benefit reporting.
A7: E5 | B7: Controlled / audited evidence | C7: Sustained outcomes plus verified control effectiveness, audit trail, governance and exception handling. | D7: Highest confidence for autonomous/agentic operating-state claims.

Sheet Calibration Waves
A1: Priority | B1: Journey | C1: Functional Wings | D1: Reason to Start | E1: Calibration Output | F1: Wave Status
A2: 1 | B2: Order-to-Cash | C2: Sales -> Inventory -> Logistics -> Finance | D2: Strongest existing digital footprint and clear management visibility. | E2: Actual process -> systems -> human touches -> KPI baseline -> S-state -> E-level -> friction -> controls -> target -> opportunity -> readiness -> business case | F2: Wave 1 provisional evidence calibration completed; live production event extraction pending
A3: 2 | B3: Source-to-Pay | C3: SCM -> Inventory/QC -> Finance | D3: Strong catalogue with material control and manual handoffs. | E3: Same calibration pack | F3: Wave 2 design pack created; execution calibration pending
A4: 3 | B4: Delivery-to-POD | C4: Sales -> Logistics -> Inventory -> Finance | D4: Highly visible manual-to-digital journey with measurable exceptions and reconciliation. | E4: Same calibration pack | F4: Wave 3 design pack created; execution calibration pending
A5: 4 | B5: Attendance-to-Payroll | C5: HR -> Finance | D5: Clear measurable productivity, accuracy and control outcome. | E5: Same calibration pack | F5: Wave 4 design pack created; execution calibration pending
A6: 5 | B6: Plan-to-Produce | C6: Sales/Planning -> Production -> QC -> Inventory -> Finance | D6: High manufacturing transformation value; requires strong control discipline. | E6: Same calibration pack | F6: Wave 5 design pack created; execution calibration pending

Sheet Field Dictionary
A1: Field | B1: Purpose / Definition | C1: Level / Type
A2: Process ID | B2: Stable enterprise identifier for the canonical process. | C2: Control
A3: L0-L6 | B3: Hierarchical process decomposition from enterprise to task/decision. | C3: Taxonomy
A4: E2E Value Stream ID | B4: Horizontal cross-functional journey link. | C4: Dimension
A5: Organization | B5: Legal entity/SBU where variant executes. | C5: Dimension
A6: Process Variant | B6: Organization-specific method or policy variant. | C6: Dimension
A7: Business Process Owner | B7: Accountable for business outcome. | C7: Governance
A8: Transformation Owner | B8: Accountable for transformation delivery. | C8: Governance
A9: Control Owner | B9: Accountable for risk/control design and operation. | C9: Governance
A10: Data Owner | B10: Accountable for source/master data quality. | C10: Governance
A11: System(s) | B11: Applications/services used by the process. | C11: Technology
A12: System of Record | B12: Authoritative source of truth. | C12: Technology
... A29: Evidence Link | B29: Direct link to transaction/log/config/SOP/UAT/control evidence. | C29: Evidence

Sheet Sources
A1: Source Type | B1: Functional Wing / Use | C1: Source Title | D1: URL | E1: Evidence Role
A2: Project / design evidence | B2: Sales | C2: Business Process Mapping Document - Primary Sales_UPDATED_SDD | D2: https://docs.google.com/document/d/1IoV-RaOxb83z2IttGlRKy863G_pckAGUegBqnRkemgc/edit?usp=drivesdk | E2: Baseline taxonomy and/or current-state evidence; does not by itself prove production maturity.
A3: Project / design evidence | B3: Finance & Accounts | C3: 04.5-ACCOUNTS-FINANCE-SDD | D3: https://docs.google.com/document/d/1opp2b-tGrMR5YcZ5IZfIjdlIIbNANJ3pPrJsKcnq5Rs/edit?usp=drivesdk | E3: Baseline taxonomy and/or current-state evidence; does not by itself prove production maturity.
A4: Project / design evidence | B4: SCM / Procurement / Commercial | C4: SCM - Signed SDD | D4: https://docs.google.com/document/d/127YQA_Z0zcKBMCFBa4ZgW_kmnExCMgfpheJ_DeoXFmw/edit?usp=drivesdk | E4: Baseline taxonomy and/or current-state evidence; does not by itself prove production maturity.
A5: Project / design evidence | B5: Inventory & Warehouse | C5: 04.1-INVENTORY-MANAGEMENT-SDD | D5: https://docs.google.com/document/d/1eGvAn9ZvGrCKaBnvot_iqCkITzAsJlsNsOteIiyCT58/edit?usp=drivesdk | E5: Baseline taxonomy and/or current-state evidence; does not by itself prove production maturity.
A6: Project / design evidence | B6: Logistics | C6: Logistics Module SDD | D6: https://docs.google.com/document/d/1doGDuain3lxIApXJtGNkRmL4FIkb1EphJ_IGoSFXJQ4/edit?usp=drivesdk | E6: Baseline taxonomy and/or current-state evidence; does not by itself prove production maturity.
A7: Project / design evidence | B7: Production / Manufacturing | C7: Business Requirement Document: Production Module (AIL) | D7: https://docs.google.com/document/d/1JZeibH6jDWNLybYCgJMq-fEYwidL32H4_BTkQFD0Ozw/edit?usp=drivesdk | E7: Baseline taxonomy and/or current-state evidence; does not by itself prove production maturity.
A8: Project / design evidence | B8: Quality Control | C8: Business Requirement Document: Production Module (AIL) - composite QC evidence | D8: https://docs.google.com/document/d/1JZeibH6jDWNLybYCgJMq-fEYwidL32H4_BTkQFD0Ozw/edit?usp=drivesdk | E8: Baseline taxonomy and/or current-state evidence; does not by itself prove production maturity.
A9: Project / design evidence | B9: Human Resources | C9: hr_module_project_management_annexes_2026-07-18 | D9: https://docs.google.com/spreadsheets/d/1XfHiOhLTJvGO_VKHyitZ8ijc_og8feRt5wAfyi8PC48/edit?usp=drivesdk | E9: Baseline taxonomy and/or current-state evidence; does not by itself prove production maturity.
A10: ERP planning / status evidence | B10: Cross-functional | C10: Erp planning final | D10: https://docs.google.com/spreadsheets/d/1umALedtbSDV1V9LXgayk7MjvL7B9ZnlNAHuD9wBdykM/edit?usp=drivesdk | E10: Timeline/status reference. Progress values should not be treated as verified process maturity without execution evidence.
A11: External reference | B11: Process taxonomy | C11: APQC Process Classification Framework (Cross Industry) | D11: https://www.apqc.org/resource-library/resource-listing/apqc-process-classification-framework-pcf-cross-industry-pdf-13 | E11: External validation for hierarchical process taxonomy and customization approach.
A12: External reference | B12: Process intelligence | C12: Microsoft Power Automate Process Mining overview | D12: https://learn.microsoft.com/en-us/power-automate/process-mining-overview | E12: External validation for event-log-based process discovery, variants, bottlenecks and automation opportunity analysis.
... A31: External reference | B31: Business Central O2C API extraction | C31: Microsoft Learn - Business Central API v2.0 / salesOrder, salesShipment, salesInvoice | D31: https://learn.microsoft.com/en-us/dynamics365/business-central/dev-itpro/api-reference/v2.0/ | E31: Validates standard REST API availability for customers and core sales-order/shipment/invoice resources; custom AGI fields still require technical schema validation.

Sheet Wave1 O2C Process Tree
A1: Process Step ID | B1: L2 Functional Wing | C1: L3 Process Group | D1: L4 Sub-process | E1: L5 Activity | F1: L6 Task / Decision | G1: Primary System | H1: System of Record | I1: Human Role | J1: Automation Mode | K1: Current State | L1: Target State | M1: Required Control | N1: Primary KPI | O1: Evidence Needed | P1: Source Title | Q1: Source URL | R1: Calibration Status
A2: O2C-001 | B2: Sales | C2: Customer & Channel Management | D2: Customer Onboarding | E2: Capture customer request | F2: Validate required fields, Customer Type, organization and territory context | G2: Sales Eco | H2: Sales Eco / BC approval status | I2: Org Admin | J2: Human + system validation | K2: Candidate S1-S2 | L2: S2 | M2: Mandatory fields; duplicate prevention; role access | N2: Digital onboarding rate | O2: Submitted customer transactions + validation/error logs | P2: BMD Sales Eco System Integration with Business Central – Solution Design | Q2: https://docs.google.com/document/d/1P3oTC3F9q076zLs0519cizrZSVzMfsoBl-hogIgGC10/edit | R2: Provisional evidence calibration complete; live production evidence pending
A3: O2C-002 | B3: Sales | C3: Customer & Channel Management | D3: Customer ERP Creation | E3: Create pending BC customer | F3: Call BC API, assign Customer No., block transactions pending approval | G3: Sales Eco + Business Central | H3: Business Central | I3: System / Finance approver | J3: Deterministic integration | K3: Candidate S2 | L3: S2 | M3: Idempotency; least-privilege integration user; audit trail | N3: Successful ERP creation rate | O3: API request/response, BC Customer record, integration log | P3: BMD Sales Eco System Integration with Business Central – Solution Design | Q3: https://docs.google.com/document/d/1P3oTC3F9q076zLs0519cizrZSVzMfsoBl-hogIgGC10/edit | R3: Provisional evidence calibration complete; live production evidence pending
A4: O2C-003 | B4: Sales / Finance | C4: Customer & Channel Management | D4: Customer Approval | E4: Approve or reject customer | F4: Review customer, approve/reject, capture reason, unblock if approved | G4: Business Central | H4: Business Central | I4: Finance / authorized approver | J4: Human approval workflow | K4: Candidate S1-S2 | L4: S2 | M4: Approval authority; blocked-until-approved; audit log | N4: Customer approval cycle time | O4: Approval entries, customer status history, approver timestamps | P4: BMD Sales Eco System Integration with Business Central – Solution Design | Q4: https://docs.google.com/document/d/1P3oTC3F9q076zLs0519cizrZSVzMfsoBl-hogIgGC10/edit | R4: Provisional evidence calibration complete; live production evidence pending
A5: O2C-004 | B5: Sales | C5: Pricing, Discount & Commercial Control | D5: Price Master Governance | E5: Create and approve price proposal | F5: Route proposal through HOD, CMO, Accounts and Management; activate approved effective price | G5: Sales Eco / ERP | H5: Approved Price Master | I5: Sales Admin, HOD, CMO, Accounts, Management | J5: Human approval + system workflow | K5: Candidate S1-S2 | L5: S2 | M5: Versioning; effective date; mandatory comments on send-back/reject | N5: Price approval cycle time | O5: Proposal versions, approval audit, activated price history | P5: Business Process Mapping Document - Primary Sales_UPDATED_SDD | Q5: https://docs.google.com/document/d/1IoV-RaOxb83z2IttGlRKy863G_pckAGUegBqnRkemgc/edit | R5: Provisional evidence calibration complete; live production evidence pending
A6: O2C-005 | B6: Sales | C6: Order Management | D6: Sales Order Intake | E6: Create customer order / sales order | F6: Select customer, item, quantity, UOM, delivery context and RC | G6: Sales Eco / Business Central | H6: Business Central for financial document | I6: Sales user | J6: Human entry + master-data validation | K6: Candidate S1-S2 | L6: S2 | M6: Active customer; valid item/UOM; valid organization/RC | N6: Order digital adoption rate | O6: Order event log, user ID, source system, timestamp | P6: Logistics Module SDD | Q6: https://docs.google.com/document/d/1doGDuain3lxIApXJtGNkRmL4FIkb1EphJ_IGoSFXJQ4/edit | R6: Provisional evidence calibration complete; live production evidence pending
A7: O2C-006 | B7: Sales / Finance | C7: Credit Management | D7: Credit Eligibility | E7: Calculate customer exposure | F7: Combine outstanding AR and pending orders; compare with customer/RC credit limit | G7: Business Central | H7: Business Central | I7: ICC / Finance | J7: Deterministic rule | K7: Candidate S2 | L7: S2 | M7: Credit limit enforced before order confirmation | N7: Credit auto-clear rate | O7: Credit limit, AR balance, pending order exposure, approval history | P7: 04.5-ACCOUNTS-FINANCE-SDD | Q7: https://docs.google.com/document/d/1opp2b-tGrMR5YcZ5IZfIjdlIIbNANJ3pPrJsKcnq5Rs/edit | R7: Provisional evidence calibration complete; live production evidence pending
A8: O2C-007 | B8: Sales / Finance | C8: Credit Management | D8: Credit Exception Approval | E8: Approve over-limit order | F8: Route exception to ICC / authorized approver based on policy | G8: Business Central | H8: Business Central | I8: ICC / Finance approver | J8: Human exception approval | K8: Candidate S1-S2 | L8: S2 | M8: No bypass; approval trail; authority limits | N8: Credit approval cycle time | O8: Approval request, decision, comments, timestamps | P8: Logistics Module SDD | Q8: https://docs.google.com/document/d/1doGDuain3lxIApXJtGNkRmL4FIkb1EphJ_IGoSFXJQ4/edit | R8: Provisional evidence calibration complete; live production evidence pending
A9: O2C-008 | B9: Sales | C9: Order Management | D9: Commercial Validation | E9: Apply price / discount | F9: Resolve standard/promotional/negotiated price and determine approval need | G9: Sales Eco / Business Central | H9: Approved Price Master / BC order | I9: Sales user / approver | J9: Rules + human exception approval | K9: Candidate S1-S2 | L9: S2 | M9: Approved price source; controlled discount threshold | N9: Manual discount exception rate | O9: Order price source, discount %, approver trail | P9: Logistics Module SDD | Q9: https://docs.google.com/document/d/1doGDuain3lxIApXJtGNkRmL4FIkb1EphJ_IGoSFXJQ4/edit | R9: Provisional evidence calibration complete; live production evidence pending
A10: O2C-009 | B10: Inventory / Sales | C10: Inventory Availability & Reservation | D10: Availability Check | E10: Check stock across warehouses | F10: Determine available/committed/reserved quantity and eligible source location | G10: Business Central | H10: Business Central | I10: System / inventory planner | J10: Deterministic rule | K10: Candidate S1-S2 | L10: S2 | M10: No negative inventory; valid warehouse/location | N10: Stock check success rate | O10: Inventory availability snapshot, reservation entries | P10: Logistics Module SDD | Q10: https://docs.google.com/document/d/1doGDuain3lxIApXJtGNkRmL4FIkb1EphJ_IGoSFXJQ4/edit | R10: Provisional evidence calibration complete; live production evidence pending
A11: O2C-010 | B11: Inventory / Sales | C11: Inventory Availability & Reservation | D11: Stock Reservation | E11: Reserve inventory | F11: Reserve stock against confirmed order and release on cancellation/expiry | G11: Business Central | H11: Business Central | I11: System | J11: Deterministic automation | K11: Candidate S2 | L11: S2 | M11: Reservation tied to confirmed order; release rule | N11: Reservation automation rate | O11: Reservation entries, release events, allocation logs | P11: Logistics Module SDD | Q11: https://docs.google.com/document/d/1doGDuain3lxIApXJtGNkRmL4FIkb1EphJ_IGoSFXJQ4/edit | R11: Provisional evidence calibration complete; live production evidence pending
A12: O2C-011 | B12: Sales / Logistics | C12: Fulfilment Coordination | D12: Delivery Order Generation | E12: Generate one or more DOs from SO | F12: Create scheduled/partial DOs while preserving parent SO and remaining balance | G12: Business Central / Logistics App | H12: Business Central | I12: Sales / logistics planner | J12: Rules + human scheduling | K12: Candidate S1-S2 | L12: S2 | M12: DO must reference SO; outstanding quantity cannot be exceeded | N12: SO-to-DO cycle time | O12: SO/DO references, quantity balances, timestamps | P12: Logistics Module SDD | Q12: https://docs.google.com/document/d/1doGDuain3lxIApXJtGNkRmL4FIkb1EphJ_IGoSFXJQ4/edit | R12: Provisional evidence calibration complete; live production evidence pending
... A30: O2C-029 | B30: Management / Cross-functional | C30: O2C Performance Management | D30: Process Monitoring | E30: Monitor end-to-end O2C performance | F30: Track throughput, cycle time, manual touches, exceptions, adoption, STP, OTIF and DSO | G30: Fabric / Power BI / process intelligence | H30: Event data from systems of record | I30: Process owner / management | J30: Analytics / process mining | K30: TBD | L30: S3 | M30: KPI lineage; common process IDs; verified event timestamps | N30: O2C end-to-end cycle time | O30: Event log across customer/order/delivery/invoice/payment | P30: Microsoft Power Automate Process Mining overview | Q30: https://learn.microsoft.com/en-us/power-automate/process-mining-overview | R30: Provisional evidence calibration complete; live production evidence pending

Sheet O2C Metric Dictionary
A1: Metric ID | B1: Metric Name | C1: KPI Family | D1: Definition | E1: Formula / Calculation | F1: Numerator | G1: Denominator | H1: Unit | I1: Grain | J1: Source Event / System | K1: Management Use | L1: Proposed Direction / Target | M1: Status
A2: M-O2C-01 | B2: O2C End-to-End Cycle Time | C2: Process Performance | D2: Elapsed time from accepted customer order to cash application/closure. | E2: Average(cash application timestamp - order accepted timestamp) | F2: N/A | G2: N/A | H2: Hours / days | I2: Order / customer / SBU | J2: Sales Eco + BC + Logistics event timestamps | K2: Shows total working-capital and service latency. | L2: Reduce vs verified baseline; no numeric target until calibrated | M2: Definition proposed
A3: M-O2C-02 | B3: Order Digital Adoption Rate | C3: Adoption | D3: Share of eligible customer orders initiated and processed through the approved digital process. | E3: Digital orders / total eligible orders | F3: Orders executed through approved system | G3: All eligible orders | H3: % | I3: SBU / channel / month | J3: Sales Eco / BC order sources | K3: Detects shadow/manual order processes. | L3: Increase toward 100%; target to be calibrated | M3: Definition proposed
A4: M-O2C-03 | B4: Human Touches per Order | C4: Human Dependency | D4: Count of distinct human actions required from order intake through cash application. | E4: Human action events / completed orders | F4: Count of human action events | G4: Completed O2C orders | H4: Touches / order | I4: Order / process step | J4: Workflow/audit logs across Sales Eco, BC, Logistics | K4: Quantifies manual reliance and automation opportunity. | L4: Reduce where controls permit | M4: Requires event classification
A5: M-O2C-04 | B5: Human Minutes per Order | C5: Human Dependency | D5: Estimated or measured active human processing time across the O2C chain. | E5: Sum active human processing minutes / completed orders | F5: Active human minutes | G5: Completed orders | H5: Minutes / order | I5: Order / role / activity | J5: Task timestamps, time study, workflow logs | K5: Supports productivity and benefit realization. | L5: Reduce vs baseline without weakening controls | M5: Requires baseline study
A6: M-O2C-05 | B6: Straight-Through Processing Rate | C6: Automation | D6: Share of eligible transactions completed through the defined scope without manual intervention. | E6: Transactions completed without manual intervention / eligible transactions | F6: No-manual-intervention transactions | G6: Eligible transactions | H6: % | I6: Process / SBU / transaction type | J6: Cross-system event log | K6: Core indicator of deterministic automation. | L6: Increase only for low-risk standardized cases | M6: Definition proposed
A7: M-O2C-06 | B7: Credit Auto-Clear Rate | C7: Automation / Control | D7: Share of eligible orders that pass credit validation without manual exception approval. | E7: Credit-cleared orders without manual approval / credit-checked orders | F7: Auto-cleared orders | G7: Credit-checked orders | H7: % | I7: Customer / RC / SBU | J7: BC credit check / approval events | K7: Shows effectiveness of standard credit rules. | L7: Increase for policy-compliant orders | M7: Definition proposed
A8: M-O2C-07 | B8: Credit Exception Rate | C8: Exception | D8: Share of credit-checked orders requiring override or exception approval. | E8: Credit exception orders / credit-checked orders | F8: Exception orders | G8: Credit-checked orders | H8: % | I8: Customer / RC / SBU | J8: BC approval workflow | K8: Highlights policy friction and customer-risk exposure. | L8: Reduce avoidable exceptions; do not suppress justified approvals | M8: Definition proposed
A9: M-O2C-08 | B9: Credit Approval Cycle Time | C9: Process Performance | D9: Elapsed time from credit exception submission to final approval/rejection. | E9: Average(decision timestamp - submission timestamp) | F9: N/A | G9: N/A | H9: Minutes / hours | I9: Exception / approver / SBU | J9: BC approval workflow | K9: Finds approval bottlenecks. | L9: Reduce vs baseline; design SDD references <4 hours as a candidate benchmark, not verified target | M9: Target requires management validation
A10: M-O2C-09 | B10: Manual Discount Exception Rate | C10: Exception / Commercial Control | D10: Share of orders requiring non-standard discount approval. | E10: Orders with discount exception / total eligible orders | F10: Discount-exception orders | G10: Eligible orders | H10: % | I10: SBU / customer / product | J10: Sales Eco / BC pricing and approval events | K10: Identifies pricing-policy leakage and process friction. | L10: Reduce avoidable exceptions; preserve approved commercial flexibility | M10: Definition proposed
A11: M-O2C-10 | B11: Stock Availability Pass Rate | C11: Fulfilment | D11: Share of order lines that can be fulfilled from eligible stock when checked. | E11: Lines passing availability check / lines checked | F11: Available order lines | G11: Lines checked | H11: % | I11: Item / location / SBU | J11: Business Central inventory availability | K11: Links inventory readiness to sales service. | L11: Increase; segment by stockout cause | M11: Definition proposed
A12: M-O2C-11 | B12: Reservation Automation Rate | C12: Automation | D12: Share of eligible confirmed order lines reserved automatically without manual allocation. | E12: Automatically reserved lines / eligible confirmed lines | F12: Automatically reserved lines | G12: Eligible confirmed lines | H12: % | I12: Item / location / SBU | J12: BC reservation entries | K12: Measures inventory-fulfilment automation. | L12: Increase for standard allocation cases | M12: Definition proposed
... A34: M-O2C-33 | B34: Digital Receipt Rate | C34: Adoption / Control | D34: Share of eligible customer receipts captured through the approved digital Money Receipt/receipt process with authoritative ERP linkage. | E34: Digitally captured and ERP-linked receipts / eligible customer receipts | F34: Receipts with approved digital source and ERP posting/reference | G34: Eligible customer receipts | H34: % | I34: SBU / bank / customer / month | J34: Sales Eco MR + Business Central receipt/ledger entries | K34: Detects off-system receipt capture and reconciliation risk. | L34: Increase toward 100% where digital receipt is mandatory | M34: Definition proposed; baseline pending

Sheet O2C Evidence Requirements
A1: Evidence ID | B1: Process Step / Area | C1: Evidence Level Supported | D1: Evidence Artifact | E1: System / Owner | F1: Required Fields | G1: Sampling Window / Frequency | H1: Validation Test | I1: Failure Signal | J1: Management Interpretation | K1: Source / URL | L1: Status
A2: EV-O2C-01 | B2: Entire O2C design baseline | C2: E1 | D2: Approved SDD/FRD/SOP and signed requirements | E2: Process owner / AESL / implementation team | F2: Process scope, actors, business rules, approvals, integrations, exceptions, target behavior | G2: Latest approved version; review on material change | H2: Confirm document approval/version and map each L4-L6 step to supporting requirement | I2: Unapproved draft; conflicting documents; missing process step | J2: Proves intended design only, not production maturity | K2: https://docs.google.com/document/d/1IoV-RaOxb83z2IttGlRKy863G_pckAGUegBqnRkemgc/edit | L2: Available; needs evidence mapping
A3: EV-O2C-02 | B3: Customer onboarding / approval | C3: E2-E3 | D3: Sales Eco and BC configuration plus production customer approval history | E3: Sales / Finance / system owner | F3: Customer ID, organization, type, status, BC Customer No., blocked state, approver, decision, timestamps | G3: Sample recent 30-90 days across active SBUs | H3: Trace submitted customer through BC creation, approval/rejection and callback | I3: Missing BC reference; unblocked before approval; approval outside system | J3: Distinguishes configured onboarding from actually governed digital onboarding | K3: https://docs.google.com/document/d/1P3oTC3F9q076zLs0519cizrZSVzMfsoBl-hogIgGC10/edit | L3: Pending production sample
A4: EV-O2C-03 | B4: Price / discount governance | C4: E2-E4 | D4: Price proposal configuration, version history and approval events | E4: Sales / Commercial | F4: Price proposal ID, item/customer scope, old/new price, effective date, approver chain, comments, activated version | G4: Recent 3 months and latest price change by SBU | H4: Reconcile approved version to price used on orders | I4: Order price not traceable to approved master; offline discount approval | J4: Supports pricing control, exception rate and cycle-time metrics | K4: https://docs.google.com/document/d/1IoV-RaOxb83z2IttGlRKy863G_pckAGUegBqnRkemgc/edit | L4: Pending configuration/event evidence
A5: EV-O2C-04 | B5: Order intake | C5: E3-E4 | D5: Production customer order / sales order event extract | E5: Sales Eco / Business Central | F5: Order ID, source, creator, customer, item, qty, UOM, RC, created/submitted/approved timestamps, status | G5: At least 30 days; preferably 90 days including all active SBUs | H5: Compare transaction counts to known/manual order population and identify off-system orders | I5: Missing source tag; duplicate orders; material manual order population | J5: Required to measure digital adoption and order cycle time | K5: https://learn.microsoft.com/en-us/dynamics365/business-central/quick-start-sell-products-and-services | L5: Pending production extract
A6: EV-O2C-05 | B6: Credit control | C6: E3-E4 | D6: Credit-check and approval workflow event log | E6: Business Central / Finance | F6: Customer, RC, credit limit, AR exposure, pending order exposure, decision, exception reason, approver, timestamps | G6: 30-90 days by SBU/RC | H6: Recalculate exposure for sample orders and verify approval only when rule requires | I6: Credit bypass; stale exposure; approval missing; approval outside system | J6: Supports auto-clear, exception, approval-time and control-effectiveness measures | K6: https://docs.google.com/document/d/1opp2b-tGrMR5YcZ5IZfIjdlIIbNANJ3pPrJsKcnq5Rs/edit | L6: Pending production extract
A7: EV-O2C-06 | B7: Stock availability / reservation | C7: E3-E4 | D7: Inventory availability snapshots and reservation entries linked to sales orders | E7: Business Central / Inventory | F7: SO line, item, location, on-hand, available, reserved, reservation timestamp, release reason | G7: 30-90 days; sample stockout and cancellation cases | H7: Trace selected order lines from availability check through reservation/release | I7: Negative stock; reservation absent; manual allocation with no record; stale availability | J7: Proves actual inventory automation and fulfilment readiness | K7: https://docs.google.com/document/d/1eGvAn9ZvGrCKaBnvot_iqCkITzAsJlsNsOteIiyCT58/edit | L7: Pending production extract
A8: EV-O2C-07 | B8: SO to DO linkage | C8: E3-E4 | D8: Sales Order / Delivery Order cross-reference extract | E8: Business Central / Logistics | F8: SO No., DO No., order qty, DO qty, delivered qty, outstanding qty, creation/status timestamps | G8: 90-day sample including partial/scheduled deliveries | H8: Confirm every DO references one valid SO and cumulative DO quantity does not exceed eligible balance | I8: Orphan DO; broken quantity balance; duplicate allocation | J8: Foundation for partial-delivery monitoring and O2C reconciliation | K8: https://learn.microsoft.com/en-us/dynamics365/business-central/sales-how-send-partial-shipments | L8: Pending production extract
A9: EV-O2C-08 | B9: Trip planning / vehicle allocation | C9: E2-E4 | D9: Trip, DO membership, route and vehicle/driver assignment log | E9: Logistics App / Logistics owner | F9: Trip ID, DO IDs, stops, vehicle, capacity, driver, eligibility checks, assignment time, override reason | G9: 30-60 days across own/hired vehicles | H9: Verify capacity/document/driver eligibility and reconstruct manual overrides | I9: Allocation outside app; missing capacity checks; invalid driver/vehicle docs | J9: Determines actual transition from spreadsheet/phone planning to digital execution | K9: https://docs.google.com/document/d/1doGDuain3lxIApXJtGNkRmL4FIkb1EphJ_IGoSFXJQ4/edit | L9: Pending production evidence
A10: EV-O2C-09 | B10: Loading execution | C10: E3-E4 | D10: Loading advice and actual loading events | E10: Logistics / Warehouse | F10: DO, item, advised qty, loaded qty, discrepancy reason, user, timestamps | G10: 30-60 days; include discrepancy cases | H10: Reconcile loaded quantity to authorized DO and subsequent DN/shipment | I10: Paper-only loading; unexplained variance; loaded quantity exceeds authorization | J10: Supports loading accuracy and human-touch analysis | K10: https://docs.google.com/document/d/1doGDuain3lxIApXJtGNkRmL4FIkb1EphJ_IGoSFXJQ4/edit | L10: Pending production evidence
A11: EV-O2C-10 | B11: Gate / weighbridge | C11: E3-E4 | D11: Digital gate-in, weighbridge and gate-out events | E11: Gate / Logistics | F11: Trip, vehicle, gate-in/out timestamps, gross/tare/net if applicable, gate document status | G11: 30-60 days by plant | H11: Match gate-out to valid loaded trip; calculate dwell; inspect missing/duplicate events | I11: Paper register only; missing timestamp; gate-out before loading completion | J11: Proves gate-control digitization and identifies plant congestion | K11: https://docs.google.com/document/d/1doGDuain3lxIApXJtGNkRmL4FIkb1EphJ_IGoSFXJQ4/edit | L11: Pending production evidence
A12: EV-O2C-11 | B12: Dispatch / in-transit | C12: E3-E4 | D12: Shipment status history and GPS/telemetry where implemented | E12: Logistics App | F12: Trip, dispatch time, status transitions, route/ETA, location events, exception events | G12: 30-60 days | H12: Check sequence/timestamps and compare dispatch schedule to actual departure | I12: Status entered retrospectively; missing location/status history | J12: Supports dispatch punctuality and actual execution visibility | K12: https://docs.google.com/document/d/1doGDuain3lxIApXJtGNkRmL4FIkb1EphJ_IGoSFXJQ4/edit | L12: Pending production evidence
... A22: EV-O2C-21 | B22: Transformation outcome verification | C22: E5 | D22: Approved baseline vs post-change KPI and benefit pack | E22: Business process owner / Finance / Transformation Office | F22: Baseline period, post-change period, volume normalization, KPI change, human hours saved, cost/value, controls, adoption, assumptions | G22: Per initiative; 30/60/90-day post-go-live and quarterly thereafter | H22: Verify same process scope, comparable volume/mix, attributable change and finance sign-off for monetary benefits | I22: Claimed benefit with no baseline; volume/mix distortion; savings not realized operationally | J22: Only E5 should be treated as realized transformation value | K22: https://learn.microsoft.com/en-us/power-automate/process-mining-overview | L22: Not available yet

Sheet Wave2 S2P Process Tree
A1: Process Step ID | B1: L2 Functional Wing | C1: L3 Process Group | D1: L4 Sub-process | E1: L5 Activity | F1: L6 Task / Decision | G1: Primary System | H1: System of Record | I1: Human Role | J1: Automation Mode | K1: Current State | L1: Target State | M1: Required Control | N1: Primary KPI | O1: Evidence Needed | P1: Source Title | Q1: Source URL | R1: Calibration Status
A2: S2P-001 | B2: SCM / Requesting Function | C2: Demand Management | D2: Demand Capture | E2: Create internal demand | F2: Capture requester, item/service, quantity, need date, purpose, priority, cost center and attachments | G2: Custom Demand / Business Central | H2: Approved demand record | I2: Requester | J2: Human entry + system validation | K2: Candidate S0-S1 | L2: S1/S2 | M2: Mandatory fields; role access; valid master data; duplicate prevention | N2: Demand digital adoption rate | O2: Demand records, source channel, user, timestamps, validation errors | P2: SCM - Signed SDD + SCM Business Central Project Annexes | Q2: https://docs.google.com/document/d/127YQA_Z0zcKBMCFBa4ZgW_kmnExCMgfpheJ_DeoXFmw/edit | R2: Not calibrated
A3: S2P-002 | B3: SCM / Inventory / Planning | C3: Demand Management | D3: Automatic Demand Generation | E3: Generate replenishment demand | F3: Use reorder points, inventory position, sales forecasts and manufacturing plans to suggest demand | G3: Business Central Requisition Worksheet / extension | H3: Business Central planning data | I3: Inventory Planner | J3: Deterministic planning rule + human review | K3: Candidate S1-S2 | L3: S2 | M3: Approved planning parameters; demand traceability; exception override reason | N3: Auto-demand generation rate | O3: Requisition worksheet suggestions, reorder parameters, acceptance/rejection events | P3: SCM - Signed SDD + Microsoft purchasing/planning guidance | Q3: https://learn.microsoft.com/en-us/dynamics365/business-central/planning-supply | R3: Not calibrated
A4: S2P-003 | B4: SCM / Requesting Function | C4: Demand Management | D4: Demand Approval | E4: Approve or reject demand | F4: Route demand/requisition to authorized approver based on policy, category, value and cost center | G4: Business Central Workflow / Custom Demand | H4: Business Central approval entry | I4: Department / Budget Approver | J4: Human approval workflow | K4: Candidate S1-S2 | L4: S2 | M4: No self-approval; delegated authority; comments/rejection reason; audit trail | N4: Demand approval cycle time | O4: Approval requests, decisions, delegation, comments, timestamps | P4: SCM Business Central Project Annexes - UAT / Fit-Gap | Q4: https://docs.google.com/spreadsheets/d/1laHtFEUFbm3VAheUpIXssk8dKZ9sCiNyWZ7nC5wg9Es/edit | R4: Not calibrated
A5: S2P-004 | B5: SCM | C5: Demand Consolidation | D5: Indent / PR Consolidation | E5: Group compatible approved demands | F5: Consolidate compatible demands by material class, vendor affinity, need date and procurement strategy | G5: Custom Indent / Business Central | H5: Approved indent / requisition | I5: SCM Buyer | J5: Rules + human consolidation | K5: Candidate S0-S1 | L5: S2 | M5: Only approved demand eligible; source-demand traceability; grouping rules | N5: Demand consolidation rate | O5: Demand-to-indent mapping, grouping rule, buyer action, timestamps | P5: SCM - Signed SDD | Q5: https://docs.google.com/document/d/127YQA_Z0zcKBMCFBa4ZgW_kmnExCMgfpheJ_DeoXFmw/edit | R5: Not calibrated
A6: S2P-005 | B6: SCM / Finance | C6: Budget & Commitment Control | D6: Budget Availability Check | E6: Validate budget before commitment | F6: Check cost-center budget/availability before requisition or PO approval and route override where permitted | G6: Business Central + Budget Extension/Integration | H6: Approved budget source | I6: SCM Buyer / Finance | J6: Deterministic validation + human override | K6: Candidate S0-S1 | L6: S2 | M6: Defined control point; no silent override; CFO authorization for approved exceptions | N6: Budget exception rate | O6: Budget balance, request value, check result, override approval | P6: SCM Business Central Project Annexes - BC Fit-Gap | Q6: https://docs.google.com/spreadsheets/d/1laHtFEUFbm3VAheUpIXssk8dKZ9sCiNyWZ7nC5wg9Es/edit | R6: Not calibrated
A7: S2P-006 | B7: SCM / Finance | C7: Budget & Commitment Control | D7: Commitment Recording | E7: Record and release procurement commitment | F7: Create approved commitment at agreed control point and release/reconcile it on PO/invoice lifecycle | G7: Business Central Extension / Finance | H7: Business Central / approved commitment ledger | I7: Finance / SCM | J7: Deterministic posting | K7: Candidate S0-S1 | L7: S2 | M7: Approved accounting treatment; reversal/reconciliation; source document traceability | N7: Commitment reconciliation rate | O7: Commitment entries, release events, PO/invoice links | P7: SCM - Signed SDD + Finance SDD | Q7: https://docs.google.com/document/d/1opp2b-tGrMR5YcZ5IZfIjdlIIbNANJ3pPrJsKcnq5Rs/edit | R7: Not calibrated
A8: S2P-007 | B8: SCM / Finance / Audit | C8: Vendor Management | D8: Vendor Registration | E8: Create vendor application | F8: Capture legal, financial, banking, tax, operational and classification details for local/foreign vendors | G8: Business Central / Vendor Onboarding Extension | H8: Business Central Vendor Master | I8: SCM Vendor Management | J8: Human entry + system validation | K8: Candidate S1 | L8: S2 | M8: Mandatory KYC/compliance fields; duplicate prevention; controlled bank details | N8: Vendor onboarding cycle time | O8: Vendor application, documents, verification events, created/approved timestamps | P8: SCM - Signed SDD | Q8: https://docs.google.com/document/d/127YQA_Z0zcKBMCFBa4ZgW_kmnExCMgfpheJ_DeoXFmw/edit | R8: Not calibrated
A9: S2P-008 | B9: SCM / Finance / Audit | C9: Vendor Management | D9: Vendor Approval & Compliance | E9: Approve vendor for procurement | F9: Verify vendor type, legal/compliance documents, bank/tax details and approval conditions before activation | G9: Business Central Workflow / Extension | H9: Business Central Vendor Master | I9: SCM / Finance Approver | J9: Human approval + deterministic controls | K9: Candidate S1-S2 | L9: S2 | M9: Inactive until approved; document expiry controls; maker-checker; change log | N9: Approved-vendor compliance rate | O9: Approval history, document expiry, active/blocked status, change log | P9: SCM - Signed SDD + Microsoft workflow guidance | Q9: https://learn.microsoft.com/en-us/dynamics365/business-central/across-workflow | R9: Not calibrated
A10: S2P-009 | B10: SCM | C10: Sourcing & RFQ | D10: RFQ Creation | E10: Create RFQ from approved indent | F10: Generate sourcing event with grouped line items, specification, deadline and approved vendor pool | G10: Custom RFQ / Purchase Quotes | H10: RFQ / Purchase Quote record | I10: SCM Buyer | J10: Rules + human sourcing | K10: Candidate S0-S1 | L10: S2 | M10: Approved source demand; controlled specification; submission deadline | N10: RFQ preparation cycle time | O10: Indent-to-RFQ mapping, line items, vendors, deadline, created time | P10: SCM - Signed SDD + BC Fit-Gap | Q10: https://docs.google.com/spreadsheets/d/1laHtFEUFbm3VAheUpIXssk8dKZ9sCiNyWZ7nC5wg9Es/edit | R10: Not calibrated
A11: S2P-010 | B11: SCM | C11: Sourcing & RFQ | D11: Vendor Shortlisting | E11: Select eligible vendors | F11: Filter approved vendors by category, risk/classification, location, compliance and sourcing policy | G11: RFQ Workspace / Vendor Master | H11: Business Central Vendor Master | I11: SCM Buyer | J11: Rule-assisted human selection | K11: Candidate S0-S1 | L11: S2/S3 | M11: Only active/eligible vendors; minimum competition rule; override justification | N11: Eligible-vendor coverage | O11: Vendor pool, eligibility criteria, invite list, override reason | P11: SCM - Signed SDD | Q11: https://docs.google.com/document/d/127YQA_Z0zcKBMCFBa4ZgW_kmnExCMgfpheJ_DeoXFmw/edit | R11: Not calibrated
A12: S2P-011 | B12: SCM | C12: Sourcing & RFQ | D12: RFQ Distribution & Tracking | E12: Issue RFQ and monitor responses | F12: Send controlled RFQ to selected vendors, track delivery, deadline, reminders and response status | G12: RFQ Workspace / Email integration | H12: RFQ event record | I12: SCM Buyer | J12: Deterministic communication + human follow-up | K12: Candidate S0-S1 | L12: S2 | M12: Single approved RFQ version; deadline control; communication audit | N12: Vendor quote response rate | O12: Invite sent/delivered, reminder, response status, timestamps | P12: SCM - Signed SDD | Q12: https://docs.google.com/document/d/127YQA_Z0zcKBMCFBa4ZgW_kmnExCMgfpheJ_DeoXFmw/edit | R12: Not calibrated
... A37: S2P-036 | B37: Management / Cross-functional | C37: S2P Performance Management | D37: End-to-End Process Monitoring | E37: Monitor Source-to-Pay performance | F37: Track demand-to-payment cycle, digital adoption, human touches, STP, exceptions, savings, supplier service, control effectiveness and realized value | G37: Fabric / Power BI / Process Intelligence | H37: Event data from Business Central and SCM systems | I37: Process Owner / Management | J37: Analytics / process mining | K37: TBD | L37: S3 | M37: Stable case IDs; event timestamps; common process taxonomy; verified KPI lineage | N37: S2P end-to-end cycle time | O37: Cross-system event log from demand through payment | P37: Microsoft Business Central + Process Intelligence validation | Q37: https://learn.microsoft.com/en-us/dynamics365/business-central/across-workflow | R37: Not calibrated

Sheet S2P Metric Dictionary
A1: Metric ID | B1: Metric Name | C1: KPI Family | D1: Definition | E1: Formula / Calculation | F1: Numerator | G1: Denominator | H1: Unit | I1: Grain | J1: Source Event / System | K1: Management Use | L1: Proposed Direction / Target | M1: Status
A2: M-S2P-01 | B2: Source-to-Pay End-to-End Cycle Time | C2: Process Performance | D2: Elapsed time from accepted demand/requisition to final supplier payment application/closure. | E2: Average(payment posted timestamp - demand accepted timestamp) | F2: N/A | G2: N/A | H2: Days | I2: Demand / PO / SBU | J2: Demand + BC procurement + AP event timestamps | K2: Shows total procurement and working-capital latency. | L2: Reduce vs verified baseline; no numeric target until calibrated | M2: Definition proposed
A3: M-S2P-02 | B3: Demand Digital Adoption Rate | C3: Adoption | D3: Share of eligible internal purchase demands captured through the approved digital process. | E3: Digital demand cases / total eligible demand cases | F3: Digitally captured demands | G3: Eligible demands | H3: % | I3: SBU / department / month | J3: Custom Demand / BC / manual demand register | K3: Detects email, paper, Excel or verbal requisition bypass. | L3: Increase toward 100% where digital demand is mandatory | M3: Definition proposed
A4: M-S2P-03 | B4: Auto-Demand Generation Rate | C4: Automation | D4: Share of eligible replenishment demands generated from approved system planning parameters without manual creation. | E4: Auto-generated eligible demands / total eligible replenishment demands | F4: Auto-generated demands | G4: Eligible replenishment demands | H4: % | I4: Item / location / SBU | J4: BC requisition worksheet / planning suggestions | K4: Measures deterministic planning automation. | L4: Increase for stable, policy-controlled item classes | M4: Definition proposed
A5: M-S2P-04 | B5: Demand Approval Cycle Time | C5: Process Performance | D5: Elapsed time from submission of a purchase demand/requisition to final approval or rejection. | E5: Average(final decision timestamp - submission timestamp) | F5: N/A | G5: N/A | H5: Hours | I5: Request / approver / SBU | J5: BC/custom approval workflow | K5: Highlights approval bottlenecks before sourcing starts. | L5: Reduce vs baseline without weakening authority controls | M5: Definition proposed
A6: M-S2P-05 | B6: Demand Consolidation Rate | C6: Efficiency | D6: Share of compatible approved demands consolidated into common sourcing packages/indents rather than sourced separately. | E6: Demands consolidated into shared indents / compatible approved demands | F6: Consolidated demands | G6: Compatible approved demands | H6: % | I6: Material class / SBU / period | J6: Demand-to-indent mapping | K6: Shows leverage of demand aggregation and RFQ workload reduction. | L6: Increase where aggregation does not harm service/lead time | M6: Definition proposed
A7: M-S2P-06 | B7: Budget Exception Rate | C7: Control / Exception | D7: Share of purchase demands or commitments requiring budget override or exception approval. | E7: Cases requiring budget exception / cases subject to budget control | F7: Budget exception cases | G7: Budget-controlled cases | H7: % | I7: Cost center / SBU / category | J7: Budget check / approval events | K7: Reveals budget-control friction and planning quality. | L7: Reduce avoidable exceptions; preserve justified overrides | M7: Definition proposed
A8: M-S2P-07 | B8: Commitment Reconciliation Rate | C8: Control / Data Quality | D8: Share of procurement commitments correctly created, released and reconciled to the associated PO/invoice lifecycle. | E8: Fully reconciled commitments / eligible commitments | F8: Reconciled commitments | G8: Eligible commitments | H8: % | I8: Commitment / cost center / SBU | J8: Commitment ledger + PO/AP references | K8: Validates committed-spend visibility and accounting integrity. | L8: Increase toward 100% after accounting design is approved | M8: Definition proposed
A9: M-S2P-08 | B9: Vendor Onboarding Cycle Time | C9: Process Performance | D9: Elapsed time from complete vendor application to activation/rejection. | E9: Average(final vendor decision timestamp - complete application timestamp) | F9: N/A | G9: N/A | H9: Days | I9: Vendor type / SBU | J9: Vendor master / approval workflow | K9: Shows friction in expanding compliant supply base. | L9: Reduce vs baseline subject to KYC/compliance requirements | M9: Definition proposed
A10: M-S2P-09 | B10: Approved Vendor Compliance Rate | C10: Control / Compliance | D10: Share of procurement-active vendors with valid approval status and required non-expired compliance documents. | E10: Active vendors meeting all compliance requirements / active vendors | F10: Compliant active vendors | G10: Active vendors | H10: % | I10: Vendor / SBU | J10: BC vendor master + document register | K10: Management assurance that sourcing only uses governed vendors. | L10: Target 100% for mandatory controls | M10: Definition proposed
A11: M-S2P-10 | B11: RFQ Preparation Cycle Time | C11: Process Performance | D11: Elapsed time from sourcing-ready approved indent to RFQ issue. | E11: Average(RFQ issued timestamp - sourcing-ready timestamp) | F11: N/A | G11: N/A | H11: Hours / days | I11: RFQ / buyer / category | J11: RFQ workspace / purchase quotes | K11: Identifies buyer preparation and handoff delay. | L11: Reduce vs baseline | M11: Definition proposed
A12: M-S2P-11 | B12: Vendor Quote Response Rate | C12: Supplier Engagement | D12: Share of invited vendors submitting valid quotations within the sourcing window. | E12: Valid quotations received / eligible vendor invitations | F12: Valid quotations | G12: Eligible invitations | H12: % | I12: RFQ / vendor / category | J12: RFQ invitation and response log | K12: Measures supplier-market engagement and sourcing competitiveness. | L12: Increase; signed SDD lists >80% as a design benchmark, not verified target | M12: Target requires validation
... A35: M-S2P-34 | B35: Realized Procurement Hours Saved | C35: Business Value | D35: Verified reduction in human processing effort attributable to implemented procurement transformation. | E35: (Baseline human minutes per case - post-change minutes per case) x actual comparable case volume / 60 | F35: Verified minutes saved x comparable volume | G35: 60 | H35: Hours / period | I35: Initiative / process / SBU | J35: Baseline study + post-change event/time evidence | K35: Converts automation into realized productivity value. | L35: Count only when baseline and post-change evidence meet E4/E5 | M35: Outcome baseline pending

Sheet S2P Evidence Requirements
A1: Evidence ID | B1: Process Step / Area | C1: Evidence Level Supported | D1: Evidence Artifact | E1: System / Owner | F1: Required Fields | G1: Sampling Window / Frequency | H1: Validation Test | I1: Failure Signal | J1: Management Interpretation | K1: Source / URL | L1: Status
A2: EV-S2P-01 | B2: Entire S2P design baseline | C2: E1 | D2: Signed SCM SDD, BC Fit-Gap, UAT catalogue, approved SOP/process maps | E2: SCM / AESL / implementation partner | F2: Scope, actors, controls, integrations, approvals, exceptions, target behavior | G2: Latest approved version; review on material change | H2: Map every L4-L6 process step to an approved requirement/configuration artifact | I2: Conflicting requirements; unapproved design; missing end-to-end step | J2: Proves intended process only; does not prove production execution | K2: https://docs.google.com/document/d/127YQA_Z0zcKBMCFBa4ZgW_kmnExCMgfpheJ_DeoXFmw/edit | L2: Available; evidence mapping required
A3: EV-S2P-02 | B3: Demand capture | C3: E2-E4 | D3: Demand configuration plus production demand transactions | E3: SCM / requesting functions | F3: Demand ID, source channel, requester, department, category, item/service, qty, need date, purpose, cost center, timestamps | G3: 30-90 days across active SBUs | H3: Compare digital demand count to manual/email/Excel demand population and trace sampled cases | I3: Material off-system demand; missing requester/cost center; duplicate requests | J3: Separates software availability from actual procurement adoption | K3: https://docs.google.com/spreadsheets/d/1laHtFEUFbm3VAheUpIXssk8dKZ9sCiNyWZ7nC5wg9Es/edit | L3: Pending production sample
A4: EV-S2P-03 | B4: Automatic replenishment demand | C4: E2-E4 | D4: Requisition worksheet/planning parameters and accepted/rejected suggestions | E4: Inventory Planning / SCM | F4: Item, location, reorder point, stock position, forecast/planning input, suggested qty/date, user action, reason | G4: Representative 30-90 days including stockout and reorder cases | H4: Recalculate suggestions for sampled items and compare actual buyer acceptance/override | I4: Manual demand despite valid planning parameters; unexplained overrides; stale parameters | J4: Proves actual deterministic planning automation and parameter quality | K4: https://learn.microsoft.com/en-us/dynamics365/business-central/planning-supply | L4: Pending configuration and event evidence
A5: EV-S2P-04 | B5: Demand / requisition approval | C5: E2-E4 | D5: Approval workflow configuration and approval history | E5: SCM / Finance / department approvers | F5: Request ID, amount, approver, limit, delegation, decision, comments, timestamps | G5: 30-90 days; include approvals, rejections, delegations and overdue cases | H5: Check authority path, self-approval controls, delegation period and decision trace | I5: Self approval; approval outside system; missing rejection reason; invalid delegate | J5: Required for approval-cycle and governance maturity claims | K5: https://learn.microsoft.com/en-us/dynamics365/business-central/across-use-workflows | L5: Pending production workflow extract
A6: EV-S2P-05 | B6: Demand consolidation / indent | C6: E2-E4 | D6: Demand-to-indent/PR mapping and grouping history | E6: SCM | F6: Demand IDs, indent/PR ID, grouping attributes, category, need date, vendor affinity, user, timestamps | G6: 60-90 days across high-volume categories | H6: Trace compatible approved demands into sourcing packages and test orphan/duplicate mappings | I6: Manual spreadsheet consolidation; orphan demand; repeated RFQ for compatible requests | J6: Shows whether sourcing workload is actually consolidated | K6: https://docs.google.com/document/d/127YQA_Z0zcKBMCFBa4ZgW_kmnExCMgfpheJ_DeoXFmw/edit | L6: Pending production evidence
A7: EV-S2P-06 | B7: Budget control | C7: E2-E4 | D7: Budget source/interface, validation result and override approval log | E7: Finance / SCM | F7: Cost center, available budget, request/PO value, check time, pass/fail, override, approver | G7: 60-90 days including insufficient-budget cases | H7: Recompute available budget for sample cases and verify failed checks cannot proceed without approved override | I7: Budget bypass; stale budget; silent override; inconsistent commitment basis | J7: Determines whether budget governance is system-enforced or procedural | K7: https://docs.google.com/spreadsheets/d/1laHtFEUFbm3VAheUpIXssk8dKZ9sCiNyWZ7nC5wg9Es/edit | L7: Architecture/configuration decision pending
A8: EV-S2P-07 | B8: Commitment accounting | C8: E2-E4 | D8: Commitment ledger/interface with PR/PO/invoice release and reconciliation events | E8: Finance | F8: Source document, cost center, commitment value, creation/release/reversal, remaining amount, GL/budget references | G8: Month-end plus 60-90 day transaction sample | H8: Trace selected commitments from source through final invoice/payment and reconcile open commitments | I8: Unreleased commitment; duplicate commitment; no source linkage; unexplained open balance | J8: Required before management can rely on committed-spend reporting | K8: https://docs.google.com/document/d/1opp2b-tGrMR5YcZ5IZfIjdlIIbNANJ3pPrJsKcnq5Rs/edit | L8: Accounting design / production evidence pending
A9: EV-S2P-08 | B9: Vendor onboarding | C9: E2-E4 | D9: Vendor applications, compliance documents and approval history | E9: SCM / Finance / Audit | F9: Vendor ID, type, legal/tax/bank details, documents, verification, status, approvers, timestamps | G9: All new vendors in last 90 days plus sampled active vendors | H9: Trace application to approved BC vendor and test required-field/document controls | I9: Active vendor without approval; duplicate vendor; undocumented bank change; expired mandatory document | J9: Proves governed vendor-master digitization | K9: https://docs.google.com/document/d/127YQA_Z0zcKBMCFBa4ZgW_kmnExCMgfpheJ_DeoXFmw/edit | L9: Pending production sample
A10: EV-S2P-09 | B10: RFQ creation / distribution | C10: E2-E4 | D10: RFQ sourcing event and vendor communication history | E10: SCM | F10: RFQ ID, source indent/PR, specification, line items, invite list, deadline, issue/reminder/response timestamps | G10: 60-90 days; all strategic/high-value events plus sample standard RFQs | H10: Confirm RFQ source approval, vendor eligibility, controlled version and response deadline | I10: Email-only RFQ; missing source requisition; unapproved vendor; uncontrolled RFQ revisions | J10: Determines actual sourcing digitization and communication traceability | K10: https://docs.google.com/document/d/127YQA_Z0zcKBMCFBa4ZgW_kmnExCMgfpheJ_DeoXFmw/edit | L10: Pending production evidence
A11: EV-S2P-10 | B11: Quotation capture | C11: E2-E4 | D11: Vendor quotations with source documents and structured commercial/technical fields | E11: SCM | F11: Vendor, quote version, submission time, item/UOM, qty, unit price, tax, freight, currency, lead time, payment terms, attachment | G11: 60-90 days; sample multiple vendor responses per RFQ | H11: Compare system quote fields to original supplier quotation and check version/deadline integrity | I11: Manual re-key without source doc; post-deadline edits; missing commercial fields | J11: Required for trusted comparative statements and savings claims | K11: https://docs.google.com/document/d/127YQA_Z0zcKBMCFBa4ZgW_kmnExCMgfpheJ_DeoXFmw/edit | L11: Pending quote samples
A12: EV-S2P-11 | B12: Comparative statement / normalization | C12: E2-E4 | D12: CS versions, normalized cost calculation and source quote links | E12: SCM / Finance | F12: Original and normalized values, FX/tax/freight/duty/insurance assumptions, scoring, rank, version, evaluator | G12: 60-90 days; include local/foreign and non-lowest selection cases | H12: Recalculate sample landed-cost comparisons and trace every field to quote/master/rate source | I12: Spreadsheet-only CS; hidden formulas; untraceable manual adjustment; stale FX/tax rate | J12: Proves digital evaluation integrity rather than document digitization only | K12: https://docs.google.com/spreadsheets/d/1laHtFEUFbm3VAheUpIXssk8dKZ9sCiNyWZ7nC5wg9Es/edit | L12: Extension/configuration evidence pending
... A27: EV-S2P-26 | B27: Transformation outcome verification | C27: E5 | D27: Approved baseline vs post-change KPI/benefit/control pack | E27: Business Process Owner / Finance / Transformation Office | F27: Baseline/post periods, normalized volume/mix, cycle time, human hours, STP, exceptions, quality, savings, controls, adoption, assumptions | G27: 30/60/90 days after go-live; quarterly thereafter | H27: Verify same process scope, comparable demand mix, attribution and control effectiveness; Finance sign-off for monetary benefit | I27: Benefit claimed from design/go-live only; no baseline; control deterioration; adoption too low | J27: Only E5 should be presented as sustained realized Source-to-Pay transformation value | K27: https://learn.microsoft.com/en-us/power-automate/process-mining-overview | L27: Not available yet

Sheet Wave3 D2POD Process Tree
A1: Process Step ID | B1: L2 Functional Wing | C1: L3 Process Group | D1: L4 Sub-process | E1: L5 Activity | F1: L6 Task / Decision | G1: Primary System | H1: System of Record | I1: Human Role | J1: Automation Mode | K1: Current State | L1: Target State | M1: Required Control | N1: Primary KPI | O1: Evidence Needed | P1: Source Title | Q1: Source URL | R1: Calibration Status
A2: D2POD-001 | B2: Sales / Logistics | C2: Fulfilment Eligibility | D2: Delivery Demand Release | E2: Confirm delivery-ready demand | F2: Validate approved SO/DO, customer, credit status, remaining quantity and delivery eligibility before logistics planning | G2: Sales Eco + Business Central | H2: Business Central | I2: Sales / Logistics Planner | J2: Rules + human exception handling | K2: Candidate S1-S2 | L2: S2 | M2: Only approved, credit-eligible demand; remaining quantity must be positive; full audit trail | N2: Eligible DO digital adoption | O2: SO/DO status, credit flag, quantity balances, release timestamp | P2: Logistics Module SDD | Q2: https://docs.google.com/document/d/1doGDuain3lxIApXJtGNkRmL4FIkb1EphJ_IGoSFXJQ4/edit | R2: Not calibrated
A3: D2POD-002 | B3: Sales / Logistics | C3: Fulfilment Eligibility | D3: Delivery Order Readiness | E3: Validate DO for planning | F3: Confirm DO references SO, customer and delivery point, has valid quantity/UOM and is not cancelled, blocked or fully delivered | G3: Business Central + Logistics App | H3: Business Central | I3: Logistics Planner | J3: Deterministic validation | K3: Candidate S1-S2 | L3: S2 | M3: No orphan DO; cumulative delivery cannot exceed source order; status integrity | N3: DO readiness pass rate | O3: DO/SO linkage, quantities, status, timestamps | P3: Logistics Module SDD | Q3: https://docs.google.com/document/d/1doGDuain3lxIApXJtGNkRmL4FIkb1EphJ_IGoSFXJQ4/edit | R3: Not calibrated
A4: D2POD-003 | B4: Logistics / Inventory | C4: Fulfilment Allocation | D4: Source Location Selection | E4: Select factory/depot/warehouse | F4: Choose eligible source location using inventory, delivery point, lead time, delivery priority and authority rules | G4: Logistics App + Business Central | H4: Business Central Inventory | I4: Logistics Planner | J4: Rule-assisted human decision | K4: Mixed S0-S1/S2 | L4: S2/S3 | M4: Only valid source locations; override reason mandatory; inventory feasibility | N4: Source location override rate | O4: Candidate locations, selected source, stock, reason, user/timestamp | P4: LogisticsDistributionPRDv1_2 + Inventory SDD | Q4: https://docs.google.com/document/d/1MLBiWLQcWNHzTkK6WuJz3X2Q1hUG8Z1RLys1HNpkLkA/edit | R4: Not calibrated
A5: D2POD-004 | B5: Inventory / Logistics | C5: Fulfilment Allocation | D5: Inventory Availability Validation | E5: Check fulfilment stock | F5: Validate on-hand, committed, reserved and available stock for the selected location before trip planning | G5: Business Central | H5: Business Central | I5: System / Inventory Planner | J5: Deterministic rule | K5: Candidate S1-S2 | L5: S2 | M5: No negative availability; correct location/item/UOM; timestamped availability basis | N5: Inventory availability pass rate | O5: Availability snapshot, item/location, qty, committed/reserved balance | P5: 04.1-INVENTORY-MANAGEMENT-SDD | Q5: https://docs.google.com/document/d/1eGvAn9ZvGrCKaBnvot_iqCkITzAsJlsNsOteIiyCT58/edit | R5: Not calibrated
A6: D2POD-005 | B6: Inventory / Logistics | C6: Fulfilment Allocation | D6: Stock Reservation | E6: Reserve/release stock | F6: Reserve eligible stock to the DO/trip and release automatically on cancellation, reassignment or expiry | G6: Business Central | H6: Business Central | I6: System / Inventory Planner | J6: Deterministic automation | K6: Candidate S1-S2 | L6: S2 | M6: Reservation linked to source demand; controlled release; no duplicate allocation | N6: Reservation automation rate | O6: Reservation entries, source DO, quantity, create/release events | P6: 04.1-INVENTORY-MANAGEMENT-SDD | Q6: https://docs.google.com/document/d/1eGvAn9ZvGrCKaBnvot_iqCkITzAsJlsNsOteIiyCT58/edit | R6: Not calibrated
A7: D2POD-006 | B7: Sales / Logistics | C7: Delivery Scheduling | D7: Delivery Priority & Commitment | E7: Set delivery window | F7: Prioritize eligible DOs and assign planned delivery/dispatch window based on customer promise, urgency, route and capacity | G7: Logistics App | H7: Logistics App + BC references | I7: Logistics Planner | J7: Human planning + rule assistance | K7: Mixed S0-S1 | L7: S2/S3 | M7: Priority policy; promised-date traceability; manual override reason | N7: Delivery schedule adherence | O7: Planned dispatch/delivery, priority, promise date, override | P7: LogisticsDistributionPRDv1_2 | Q7: https://docs.google.com/document/d/1MLBiWLQcWNHzTkK6WuJz3X2Q1hUG8Z1RLys1HNpkLkA/edit | R7: Not calibrated
A8: D2POD-007 | B8: Logistics | C8: Trip Planning & Consolidation | D8: Trip Consolidation | E8: Group delivery orders into trip | F8: Consolidate compatible DOs by source, route, delivery window, product constraints and vehicle capacity | G8: Logistics App | H8: Logistics App | I8: Logistics Planner | J8: Human planning; candidate optimization | K8: Mixed S0-S1 | L8: S2/S3 | M8: No incompatible load; all DOs eligible; source quantity preserved | N8: Trip consolidation rate | O8: Trip ID, DO membership, source, constraints, planner/timestamp | P8: LogisticsDistributionPRDv1_2 | Q8: https://docs.google.com/document/d/1MLBiWLQcWNHzTkK6WuJz3X2Q1hUG8Z1RLys1HNpkLkA/edit | R8: Not calibrated
A9: D2POD-008 | B9: Logistics | C9: Trip Planning & Consolidation | D9: Route & Stop Sequencing | E9: Plan route and stop order | F9: Define delivery stops and sequence considering geography, commitments, vehicle constraints and operational rules | G9: Logistics App / Mapping | H9: Logistics App | I9: Logistics Planner | J9: Human planning; candidate optimization | K9: Mixed S0-S1 | L9: S2/S3 | M9: Customer delivery constraints; route feasibility; override trace | N9: Route-plan adherence | O9: Planned sequence, actual sequence, distance/time, override reason | P9: LogisticsDistributionPRDv1_2 | Q9: https://docs.google.com/document/d/1MLBiWLQcWNHzTkK6WuJz3X2Q1hUG8Z1RLys1HNpkLkA/edit | R9: Not calibrated
A10: D2POD-009 | B10: Logistics | C10: Trip Planning & Consolidation | D10: Payload Planning | E10: Calculate planned load | F10: Check weight/volume/product compatibility against practical and legal vehicle capacity before assignment | G10: Logistics App | H10: Logistics App + Vehicle Master | I10: Logistics Planner | J10: Deterministic calculation + human review | K10: Candidate S0-S1 | L10: S2 | M10: No overload; approved capacity basis; product/load compatibility | N10: Payload load factor | O10: Planned quantity/weight/volume, vehicle capacity, constraint checks | P10: Logistics Module SDD | Q10: https://docs.google.com/document/d/1doGDuain3lxIApXJtGNkRmL4FIkb1EphJ_IGoSFXJQ4/edit | R10: Not calibrated
A11: D2POD-010 | B11: Logistics | C11: Vehicle / Transporter Allocation | D11: Transport Mode Selection | E11: Select own vs hired/transporter | F11: Choose eligible transport source based on availability, route, capacity, approved transporter/rate and policy | G11: Logistics App | H11: Logistics App / Transporter Master | I11: Logistics Planner | J11: Rule-assisted human decision | K11: Mixed S0-S1 | L11: S2/S3 | M11: Approved transporter/rate; conflict control; override reason | N11: Own-vs-hired transport mix | O11: Mode selection, transporter, rate, reason, availability | P11: LogisticsDistributionPRDv1_2 | Q11: https://docs.google.com/document/d/1MLBiWLQcWNHzTkK6WuJz3X2Q1hUG8Z1RLys1HNpkLkA/edit | R11: Not calibrated
A12: D2POD-011 | B12: Logistics | C12: Vehicle / Transporter Allocation | D12: Vehicle Eligibility | E12: Validate candidate vehicle | F12: Check capacity, availability, permits, insurance, fitness, route restrictions and document validity | G12: Logistics App / Vehicle Master | H12: Logistics App | I12: Logistics Planner / Fleet | J12: Deterministic eligibility + human selection | K12: Mixed S0-S1 | L12: S2 | M12: Expired/ineligible vehicle blocked; capacity respected; exception approval | N12: Vehicle eligibility pass rate | O12: Vehicle master, document expiry, capacity, assignment and override | P12: Logistics Module SDD | Q12: https://docs.google.com/document/d/1doGDuain3lxIApXJtGNkRmL4FIkb1EphJ_IGoSFXJQ4/edit | R12: Not calibrated
... A33: D2POD-032 | B33: Management / Cross-functional | C33: Logistics Performance Management | D33: D2POD Process Monitoring | E33: Monitor delivery-to-POD performance | F33: Track cycle time, human touches, STP, utilization, loading/gate delay, OTIF, POD, exceptions, cost, adoption and realized benefit | G33: Fabric / Power BI / Process Mining | H33: Event data from systems of record | I33: Process Owner / Management | J33: Analytics / process mining | K33: TBD | L33: S3 | M33: Case IDs; event timestamps; common process IDs; KPI lineage; production evidence | N33: D2POD end-to-end cycle time | O33: Cross-system event log from delivery release through POD/settlement | P33: Microsoft Power Automate Process Mining | Q33: https://learn.microsoft.com/en-us/power-automate/process-mining-overview | R33: Not calibrated

Sheet D2POD Metric Dictionary
A1: Metric ID | B1: Metric Name | C1: KPI Family | D1: Definition | E1: Formula / Calculation | F1: Numerator | G1: Denominator | H1: Unit | I1: Grain | J1: Source Event / System | K1: Management Use | L1: Proposed Direction / Target | M1: Status
A2: M-D2POD-01 | B2: Delivery-to-POD End-to-End Cycle Time | C2: Process Performance | D2: Elapsed time from delivery-ready release to completed POD/closed delivery outcome. | E2: Average(POD/closure timestamp - delivery-ready timestamp) | F2: N/A | G2: N/A | H2: Hours / days | I2: DO / trip / SBU | J2: Sales/BC + Logistics event timestamps | K2: Primary end-to-end service and execution latency measure. | L2: Reduce vs verified baseline | M2: Definition proposed
A3: M-D2POD-02 | B3: Eligible DO Digital Adoption | C3: Adoption | D3: Share of eligible delivery orders planned and executed through the approved digital logistics flow. | E3: Digitally processed eligible DOs / total eligible DOs | F3: Digitally processed eligible DOs | G3: Eligible DOs | H3: % | I3: SBU / plant / month | J3: BC + Logistics App + manual register | K3: Detects spreadsheet/phone/paper bypass. | L3: Increase toward 100% where mandatory | M3: Definition proposed
A4: M-D2POD-03 | B4: DO Readiness Pass Rate | C4: Control / Data Quality | D4: Share of DOs passing all eligibility and data checks on first evaluation. | E4: DOs passing first check / DOs checked | F4: DOs passing first check | G4: DOs checked | H4: % | I4: SBU / plant / reason | J4: BC + Logistics validation events | K4: Shows upstream data/process quality entering logistics. | L4: Increase; analyze failures by cause | M4: Definition proposed
A5: M-D2POD-04 | B5: DO-Ready-to-Trip-Plan Cycle Time | C5: Process Performance | D5: Elapsed time from DO readiness to assignment to an approved trip plan. | E5: Average(trip-plan timestamp - DO-ready timestamp) | F5: N/A | G5: N/A | H5: Hours | I5: DO / SBU / plant | J5: BC + Logistics App | K5: Identifies planning backlog and capacity delay. | L5: Reduce vs baseline | M5: Definition proposed
A6: M-D2POD-05 | B6: Source Location Override Rate | C6: Exception / Planning | D6: Share of source-location decisions manually changed from the system/rule recommendation or default. | E6: Overridden source decisions / source decisions with recommendation | F6: Overridden source decisions | G6: Source decisions with recommendation | H6: % | I6: Plant / route / item / SBU | J6: Logistics allocation events | K6: Reveals rule weakness, stock-data issues or legitimate planner judgment. | L6: Reduce avoidable overrides; preserve justified exceptions | M6: Definition proposed
A7: M-D2POD-06 | B7: Inventory Availability Pass Rate | C7: Fulfilment | D7: Share of eligible delivery lines with sufficient available stock at selected source when planned. | E7: Lines with sufficient stock / lines checked | F7: Lines with sufficient stock | G7: Lines checked | H7: % | I7: Item / location / SBU | J7: Business Central inventory availability | K7: Connects inventory quality to delivery readiness. | L7: Increase; segment stockout causes | M7: Definition proposed
A8: M-D2POD-07 | B8: Reservation Automation Rate | C8: Automation | D8: Share of eligible delivery lines reserved automatically without manual allocation. | E8: Automatically reserved lines / eligible lines | F8: Automatically reserved lines | G8: Eligible lines | H8: % | I8: Item / source / SBU | J8: BC reservation entries | K8: Shows inventory-allocation automation. | L8: Increase for standardized cases | M8: Definition proposed
A9: M-D2POD-08 | B9: Delivery Schedule Adherence | C9: Service / Planning | D9: Share of deliveries executed within the committed planning window. | E9: Deliveries within committed window / scheduled deliveries | F9: Deliveries within committed window | G9: Scheduled deliveries | H9: % | I9: Customer / route / SBU | J9: Logistics schedule + actual events | K9: Measures planning reliability separately from final OTIF. | L9: Increase | M9: Definition proposed
A10: M-D2POD-09 | B10: Trip Consolidation Rate | C10: Efficiency | D10: Share of eligible DOs combined into multi-order trips where consolidation is operationally valid. | E10: DOs in consolidated trips / consolidation-eligible DOs | F10: DOs in consolidated trips | G10: Consolidation-eligible DOs | H10: % | I10: Route / plant / SBU | J10: Trip plan + DO membership | K10: Shows planning efficiency and potential transport-cost leverage. | L10: Optimize, not maximize indiscriminately | M10: Definition proposed
A11: M-D2POD-10 | B11: Route Plan Adherence | C11: Execution / Planning | D11: Share of trips following the planned stop sequence/route within defined tolerance. | E11: Trips within route/sequence tolerance / tracked trips | F11: Trips within tolerance | G11: Tracked trips | H11: % | I11: Trip / route / SBU | J11: Logistics App + GPS | K11: Highlights planning quality, field deviation and route-control issues. | L11: Increase where route control is applicable | M11: Definition proposed
A12: M-D2POD-11 | B12: Payload Load Factor | C12: Asset / Logistics Efficiency | D12: Actual loaded weight/volume as a share of practical authorized capacity. | E12: Actual load / practical authorized capacity | F12: Actual load | G12: Practical authorized capacity | H12: % | I12: Trip / vehicle / route | J12: Loading + vehicle master | K12: Supports capacity and transport-cost optimization. | L12: Optimize within legal and safety limits | M12: Definition proposed
... A46: M-D2POD-45 | B46: Realized Transport Cost Saving | C46: Business Value | D46: Verified transport cost reduction attributable to the transformation after normalizing for volume, route mix and service level. | E46: Normalized baseline transport cost - normalized post-change transport cost | F46: Normalized baseline cost minus post-change cost | G46: N/A | H46: BDT / period | I46: Initiative / route / SBU | J46: Approved cost data + baseline/post-change delivery mix | K46: Tracks actual financial value rather than projected savings. | L46: Positive only when Finance/process owner verifies attribution | M46: Outcome baseline pending

Sheet D2POD Evidence Requirements
A1: Evidence ID | B1: Process Step / Area | C1: Evidence Level Supported | D1: Evidence Artifact | E1: System / Owner | F1: Required Fields | G1: Sampling Window / Frequency | H1: Validation Test | I1: Failure Signal | J1: Management Interpretation | K1: Source / URL | L1: Status
A2: EV-D2POD-01 | B2: Entire D2POD design baseline | C2: E1 | D2: Approved PRD/SDD/SOP/process maps and business rules | E2: Logistics / AESL / process owner | F2: Scope, actors, states, business rules, approvals, exceptions, integrations, target behavior | G2: Latest approved version; review on material change | H2: Map every D2POD L4-L6 step to approved requirement/process evidence | I2: Draft/conflicting design; missing step; unsigned requirement | J2: Proves intended design only, not live execution | K2: https://docs.google.com/document/d/1MLBiWLQcWNHzTkK6WuJz3X2Q1hUG8Z1RLys1HNpkLkA/edit | L2: Available; evidence mapping pending
A3: EV-D2POD-02 | B3: DO readiness / delivery release | C3: E2-E4 | D3: DO/SO configuration plus production release/readiness events | E3: Sales / Logistics / Business Central | F3: SO No., DO No., customer, qty, UOM, status, credit/release flag, ready timestamp | G3: 30-90 days across active SBUs | H3: Sample DOs and verify source order, approved quantity, status and release controls | I3: Orphan DO; manual release with no record; invalid or over-quantity DO | J3: Establishes whether delivery demand enters logistics through a governed digital gate | K3: https://docs.google.com/document/d/1doGDuain3lxIApXJtGNkRmL4FIkb1EphJ_IGoSFXJQ4/edit | L3: Pending production sample
A4: EV-D2POD-03 | B4: Source location allocation | C4: E3-E4 | D4: Allocation decision/event log | E4: Logistics / Inventory | F4: DO, item, candidate sources, stock basis, selected source, reason, override, user/time | G4: 30-60 days across plants/depots | H4: Reconstruct sample allocation decisions and verify selected source was eligible and inventory-feasible | I4: Phone/spreadsheet allocation; no basis; frequent unexplained override | J4: Measures actual transition from planner memory to governed allocation | K4: https://docs.google.com/document/d/1MLBiWLQcWNHzTkK6WuJz3X2Q1hUG8Z1RLys1HNpkLkA/edit | L4: Pending production evidence
A5: EV-D2POD-04 | B5: Inventory availability & reservation | C5: E3-E4 | D5: Availability snapshots and reservation entries linked to DO/order | E5: Business Central / Inventory | F5: Item, location, on-hand, committed, reserved, available, reservation qty/time, release reason | G5: 30-90 days; include stockout/cancellation cases | H5: Trace sample delivery lines from availability check through reservation/release | I5: Negative availability; duplicate allocation; reservation missing or stale | J5: Proves inventory readiness and allocation automation | K5: https://docs.google.com/document/d/1eGvAn9ZvGrCKaBnvot_iqCkITzAsJlsNsOteIiyCT58/edit | L5: Pending production extract
A6: EV-D2POD-05 | B6: Delivery scheduling | C6: E3-E4 | D6: Planned dispatch/delivery schedule and revisions | E6: Logistics Planner | F6: DO, priority, promise date, planned dispatch/delivery, revision, override reason, planner | G6: 30-60 days | H6: Compare commitments and priority policy to planned windows and subsequent actuals | I6: No digital plan; repeated unrecorded rescheduling; promise not linked | J6: Supports planning adherence and separates planning from execution failure | K6: https://docs.google.com/document/d/1MLBiWLQcWNHzTkK6WuJz3X2Q1hUG8Z1RLys1HNpkLkA/edit | L6: Pending production evidence
A7: EV-D2POD-06 | B7: Trip consolidation | C7: E3-E4 | D7: Trip plan and DO membership history | E7: Logistics App / Logistics | F7: Trip ID, DO IDs, source, load constraints, planned stops, planner, created/approved time | G7: 30-60 days | H7: Verify trip membership is traceable, eligible and quantities do not duplicate across active trips | I7: Spreadsheet-only trip; duplicate DO assignment; untraceable consolidation | J7: Proves trip planning is digitally governed | K7: https://docs.google.com/document/d/1MLBiWLQcWNHzTkK6WuJz3X2Q1hUG8Z1RLys1HNpkLkA/edit | L7: Pending production evidence
A8: EV-D2POD-07 | B8: Route / stop sequencing | C8: E3-E4 | D8: Planned route/stop sequence and actual route history | E8: Logistics App / GPS | F8: Trip, planned stops/order, actual stops/order, route, override reason, time/location events | G8: 30-60 days for tracked trips | H8: Compare planned versus actual sequence/route and investigate material deviations | I8: No actual route evidence; retrospective status only; unexplained deviations | J8: Supports route adherence and future optimization readiness | K8: https://docs.google.com/document/d/1MLBiWLQcWNHzTkK6WuJz3X2Q1hUG8Z1RLys1HNpkLkA/edit | L8: Pending tracking evidence
A9: EV-D2POD-08 | B9: Payload / capacity planning | C9: E3-E4 | D9: Planned load and vehicle capacity check | E9: Logistics / Vehicle Master | F9: Trip, planned weight/volume/qty, vehicle capacity, constraint checks, override | G9: 30-60 days | H9: Recalculate load factor and verify no trip exceeds approved capacity basis | I9: Missing capacity master; overload; manual calculation not recorded | J9: Supports utilization and safety/control reporting | K9: https://docs.google.com/document/d/1doGDuain3lxIApXJtGNkRmL4FIkb1EphJ_IGoSFXJQ4/edit | L9: Pending production evidence
A10: EV-D2POD-09 | B10: Vehicle / transporter eligibility | C10: E2-E4 | D10: Vehicle/transporter master plus assignment eligibility events | E10: Fleet / Logistics | F10: Vehicle, transporter, capacity, document expiry, availability, compliance status, assignment, override | G10: Current master + 30-60 day assignments | H10: Sample assignments and prove eligibility at assignment time | I10: Expired document; inactive transporter; phone allocation without eligibility check | J10: Shows control maturity before assignment automation | K10: https://docs.google.com/document/d/1doGDuain3lxIApXJtGNkRmL4FIkb1EphJ_IGoSFXJQ4/edit | L10: Pending master and assignment evidence
A11: EV-D2POD-10 | B11: Driver assignment | C11: E3-E4 | D11: Driver master and trip assignment log | E11: Fleet / Logistics | F11: Driver, license/authorization validity, availability, trip, vehicle, assignment time | G11: 30-60 days | H11: Verify assigned driver was eligible and not double-booked at assignment time | I11: Invalid license; no digital assignment; overlapping trip assignments | J11: Supports driver compliance and allocation controls | K11: https://docs.google.com/document/d/1doGDuain3lxIApXJtGNkRmL4FIkb1EphJ_IGoSFXJQ4/edit | L11: Pending production evidence
A12: EV-D2POD-11 | B12: Loading advice / warehouse pick | C12: E2-E4 | D12: Loading advice and BC warehouse/inventory pick documents | E12: Warehouse / Logistics / Business Central | F12: Trip, DO, item, source bin/location, qty to pick/load, pick qty, worker, timestamps | G12: 30-60 days across active warehouses | H12: Trace source delivery through loading advice/pick and verify quantity/bin/source consistency | I12: Paper-only pick; no source linkage; unrecorded short-pick | J12: Proves warehouse-to-logistics digital handoff | K12: https://learn.microsoft.com/en-us/dynamics365/business-central/design-details-outbound-warehouse-flow | L12: Pending production evidence
... A29: EV-D2POD-28 | B29: Transformation outcome verification | C29: E5 | D29: Approved baseline vs post-change KPI and benefit pack | E29: Business Process Owner / Finance / Transformation Office | F29: Baseline/post period, normalized volume/route mix, KPI change, hours saved, transport cost, controls, adoption, assumptions | G29: Per initiative; 30/60/90-day post-go-live and quarterly thereafter | H29: Verify comparable scope/mix, attributable change and Finance/process-owner sign-off | I29: Claimed savings with no baseline; mix distortion; control degradation; benefit not realized | J29: Only E5 should be treated as verified realized transformation value | K29: https://learn.microsoft.com/en-us/power-automate/process-mining-overview | L29: Not available yet

Sheet Wave4 A2P Process Tree
A1: Process Step ID | B1: L2 Functional Wing | C1: L3 Process Group | D1: L4 Sub-process | E1: L5 Activity | F1: L6 Task / Decision | G1: Primary System | H1: System of Record | I1: Human Role | J1: Automation Mode | K1: Current State | L1: Target State | M1: Required Control | N1: Primary KPI | O1: Evidence Needed | P1: Source Title | Q1: Source URL | R1: Calibration Status
A2: A2P-001 | B2: HR / Payroll | C2: Workforce Eligibility | D2: Employee Payroll Population | E2: Determine in-scope employees | F2: Build payroll-eligible population by company, employment status, effective dates and approved exclusions before attendance/payroll processing. | G2: HR ISV + Business Central references | H2: Authoritative HR employee source | I2: HR / Payroll Operations | J2: Rules + human exception handling | K2: Candidate S0-S1 | L2: S2 | M2: One authoritative employee population; effective-date integrity; approved exclusion reason | N2: Payroll population completeness | O2: Employee status, company, join/exit/effective dates, exclusion reason | P2: HR Module Project Management Annexes | Q2: https://docs.google.com/spreadsheets/d/1XfHiOhLTJvGO_VKHyitZ8ijc_og8feRt5wAfyi8PC48/edit | R2: Not calibrated
A3: A2P-002 | B3: HR Operations | C3: Time Planning | D3: Calendar & Holiday Setup | E3: Maintain work calendar | F3: Apply company/SBU calendars, weekly offs and approved holidays to attendance processing. | G3: HR ISV | H3: HR ISV | I3: HR Operations | J3: Configured rules | K3: Candidate S0-S1 | L3: S2 | M3: Approved calendar version; effective dating; no retrospective change without audit | N3: Calendar configuration accuracy | O3: Calendar, holiday, company/SBU, effective dates, change log | P3: HR Module Project Management Annexes | Q3: https://docs.google.com/spreadsheets/d/1XfHiOhLTJvGO_VKHyitZ8ijc_og8feRt5wAfyi8PC48/edit | R3: Not calibrated
A4: A2P-003 | B4: HR Operations | C4: Time Planning | D4: Shift & Roster Assignment | E4: Assign employee roster | F4: Assign shift/roster by employee or approved group with effective dates and approved schedule exceptions. | G4: HR ISV | H4: HR ISV | I4: HR Operations / Line Manager | J4: Rule-assisted human planning | K4: Candidate S0-S1 | L4: S2 | M4: No overlapping roster; effective dates; manager/HR authorization for change | N4: Roster coverage rate | O4: Employee, shift, roster dates, assignment/change user and approval | P4: HR Module Project Management Annexes | Q4: https://docs.google.com/spreadsheets/d/1XfHiOhLTJvGO_VKHyitZ8ijc_og8feRt5wAfyi8PC48/edit | R4: Not calibrated
A5: A2P-004 | B5: HR Operations | C5: Attendance Capture | D5: Clock-In / Clock-Out | E5: Capture raw attendance event | F5: Capture employee clock-in/out from biometric/device or approved digital source with employee and timestamp identity. | G5: Biometric / Attendance Device | H5: Attendance source + HR ISV after ingestion | I5: Employee | J5: Device/digital capture | K5: Candidate S0-S1 | L5: S2 | M5: Immutable source timestamp; employee/device identity; duplicate-event handling | N5: Attendance digital capture rate | O5: Employee ID, device, clock event, timestamp, source status | P5: HR Module Project Management Annexes | Q5: https://docs.google.com/spreadsheets/d/1XfHiOhLTJvGO_VKHyitZ8ijc_og8feRt5wAfyi8PC48/edit | R5: Not calibrated
A6: A2P-005 | B6: HR / Integration | C6: Attendance Capture | D6: Attendance Device Integration | E6: Ingest attendance events | F6: Transfer attendance events from device/system into HR ISV through approved API/file method with retry and daily control totals. | G6: Integration Layer + HR ISV | H6: HR ISV | I6: System / HR Operations exception owner | J6: Deterministic integration | K6: Candidate S0-S1 | L6: S2 | M6: Idempotent ingestion; failed-record queue; daily source-target reconciliation | N6: Attendance ingestion completeness | O6: Source/target counts, rejected events, retry status, correlation IDs | P6: HR Module Project Management Annexes | Q6: https://docs.google.com/spreadsheets/d/1XfHiOhLTJvGO_VKHyitZ8ijc_og8feRt5wAfyi8PC48/edit | R6: Not calibrated
A7: A2P-006 | B7: HR Operations | C7: Attendance Processing | D7: Attendance Classification | E7: Calculate attendance status | F7: Match punches to roster/calendar and calculate present, absent, late, early departure and payable time according to approved policy. | G7: HR ISV | H7: HR ISV | I7: System / HR Operations | J7: Deterministic rules | K7: Candidate S0-S1 | L7: S2 | M7: Versioned attendance rules; traceable source events; no silent manual override | N7: Attendance calculation first-pass rate | O7: Roster, punches, calculated status, policy/rule version | P7: HR Module Project Management Annexes | Q7: https://docs.google.com/spreadsheets/d/1XfHiOhLTJvGO_VKHyitZ8ijc_og8feRt5wAfyi8PC48/edit | R7: Not calibrated
A8: A2P-007 | B8: HR Operations | C8: Attendance Processing | D8: Attendance Exception Detection | E8: Detect missing/invalid attendance | F8: Flag missing punches, impossible sequences, unmatched device identities, roster conflicts and policy exceptions for resolution. | G8: HR ISV | H8: HR ISV | I8: HR Operations / Manager | J8: Rules + exception queue | K8: Candidate S0-S1 | L8: S2/S3 | M8: Defined exception taxonomy; owner and SLA; no payroll use while unresolved if material | N8: Attendance exception rate | O8: Exception type, employee/date, source events, owner, timestamps | P8: HR Module Project Management Annexes | Q8: https://docs.google.com/spreadsheets/d/1XfHiOhLTJvGO_VKHyitZ8ijc_og8feRt5wAfyi8PC48/edit | R8: Not calibrated
A9: A2P-008 | B9: Employee / HR | C9: Attendance Correction | D9: Correction Request | E9: Submit attendance correction | F9: Employee/authorized user submits correction with date, requested change, reason and supporting evidence where required. | G9: ESS / HR ISV | H9: HR ISV | I9: Employee / HR Operations | J9: Digital workflow initiation | K9: Candidate S0-S1 | L9: S2 | M9: Reason mandatory; original event preserved; requestor cannot self-approve | N9: Attendance correction rate | O9: Original/new value, reason, evidence, requester, timestamp | P9: HR Module Project Management Annexes | Q9: https://docs.google.com/spreadsheets/d/1XfHiOhLTJvGO_VKHyitZ8ijc_og8feRt5wAfyi8PC48/edit | R9: Not calibrated
A10: A2P-009 | B10: Manager / HR | C10: Attendance Correction | D10: Correction Approval | E10: Approve/reject correction | F10: Route correction to authorized manager/HR role; apply approved correction while preserving original data and approval history. | G10: HR ISV Workflow | H10: HR ISV | I10: Line Manager / HR Approver | J10: Workflow + human approval | K10: Candidate S0-S1 | L10: S2 | M10: Delegation control; SoD; approval timestamp; immutable before/after audit | N10: Attendance correction cycle time | O10: Request, approver, decision, timestamps, before/after values | P10: HR Module Project Management Annexes | Q10: https://docs.google.com/spreadsheets/d/1XfHiOhLTJvGO_VKHyitZ8ijc_og8feRt5wAfyi8PC48/edit | R10: Not calibrated
A11: A2P-010 | B11: HR Operations | C11: Leave Integration | D11: Approved Leave Application | E11: Apply approved leave to attendance | F11: Apply approved leave dates/types to attendance and payable-time calculation without duplicate manual entry. | G11: HR ISV Leave + Attendance | H11: HR ISV | I11: System / HR Operations | J11: Deterministic integration | K11: Candidate S0-S1 | L11: S2 | M11: Only approved leave; balance integrity; no overlap with incompatible statuses | N11: Leave-to-attendance sync rate | O11: Leave request/approval, leave dates, attendance outcome, balance | P11: HR Module Project Management Annexes | Q11: https://docs.google.com/spreadsheets/d/1XfHiOhLTJvGO_VKHyitZ8ijc_og8feRt5wAfyi8PC48/edit | R11: Not calibrated
A12: A2P-011 | B12: HR Operations / Payroll | C12: Payable Time | D12: Overtime Calculation | E12: Calculate eligible overtime | F12: Calculate overtime from approved attendance/roster and policy rules before approval or payroll inclusion. | G12: HR ISV | H12: HR ISV | I12: System / HR Operations | J12: Deterministic rules | K12: Candidate S0-S1 | L12: S2 | M12: Approved policy/rate basis; capped/eligibility rules; traceable hours | N12: Overtime calculation exception rate | O12: Attendance hours, eligible OT hours, rule/rate basis, exceptions | P12: HR Module Project Management Annexes | Q12: https://docs.google.com/spreadsheets/d/1XfHiOhLTJvGO_VKHyitZ8ijc_og8feRt5wAfyi8PC48/edit | R12: Not calibrated
... A36: A2P-035 | B36: Management / HR / Finance | C36: Payroll Performance Management | D36: A2P Process Monitoring | E36: Monitor attendance-to-payroll performance | F36: Track cycle time, digital adoption, exceptions, human touches, payroll accuracy, approval/payment timeliness, posting/reconciliation and realized benefit. | G36: Fabric / Power BI / Process Mining | H36: Event data from HR ISV, devices, bank and Business Central | I36: Process Owner / Management | J36: Analytics / process mining | K36: TBD | L36: S3 | M36: Stable case IDs; event timestamps; KPI lineage; privacy minimization; production evidence | N36: Attendance-to-payroll end-to-end cycle time | O36: Cross-system event log from attendance period through payment/posting/reconciliation | P36: Microsoft Power Automate Process Mining | Q36: https://learn.microsoft.com/en-us/power-automate/process-mining-overview | R36: Not calibrated

Sheet A2P Metric Dictionary
A1: Metric ID | B1: Metric Name | C1: KPI Family | D1: Definition | E1: Formula / Calculation | F1: Numerator | G1: Denominator | H1: Unit | I1: Grain | J1: Source Event / System | K1: Management Use | L1: Proposed Direction / Target | M1: Status
A2: M-A2P-01 | B2: Attendance-to-Payroll End-to-End Cycle Time | C2: Process Performance | D2: Elapsed time from attendance-period readiness/start of close through completed salary payment and payroll-to-GL reconciliation. | E2: Average(final reconciliation/payment completion - attendance close-start/period-ready timestamp) | F2: N/A | G2: N/A | H2: Hours / days | I2: Payroll period / company / SBU | J2: HR ISV + bank + Business Central events | K2: Primary end-to-end payroll processing latency measure. | L2: Reduce vs verified baseline without weakening controls | M2: Definition proposed
A3: M-A2P-02 | B3: Payroll Population Completeness | C3: Data Quality / Control | D3: Share of expected payroll-eligible employees correctly included or explicitly excluded with approved reason. | E3: Correctly included + approved excluded employees / expected payroll population | F3: Correctly accounted employees | G3: Expected payroll population | H3: % | I3: Company / SBU / period | J3: HR employee master + payroll run population | K3: Prevents omitted or unauthorized payroll records. | L3: Increase toward 100% | M3: Definition proposed
A4: M-A2P-03 | B4: Roster Coverage Rate | C4: Planning / Data Quality | D4: Share of roster-required employees with a valid work schedule for all required days before attendance processing. | E4: Employees/days with valid roster / roster-required employee-days | F4: Covered employee-days | G4: Roster-required employee-days | H4: % | I4: SBU / department / period | J4: HR ISV roster | K4: Shows whether attendance exceptions originate from planning gaps. | L4: Increase toward 100% where roster is mandatory | M4: Definition proposed
A5: M-A2P-04 | B5: Attendance Digital Capture Rate | C5: Adoption | D5: Share of required attendance events captured through approved biometric/digital channels rather than manual entry. | E5: Approved digital attendance events / required attendance events | F5: Digital attendance events | G5: Required attendance events | H5: % | I5: Device / site / SBU / employee type | J5: Attendance devices + HR ISV | K5: Detects paper/spreadsheet/manual attendance dependency. | L5: Increase toward 100% where digital capture is required | M5: Definition proposed
A6: M-A2P-05 | B6: Attendance Ingestion Completeness | C6: Integration / Data Quality | D6: Share of source device attendance events successfully ingested once into HR ISV within the defined service window. | E6: Successfully reconciled ingested events / source events | F6: Reconciled ingested events | G6: Source events | H6: % | I6: Device / site / day | J6: Device interface + HR ISV | K6: Tests attendance integration reliability. | L6: Increase toward 100% | M6: Definition proposed
A7: M-A2P-06 | B7: Attendance Calculation First-Pass Rate | C7: Process Quality | D7: Share of employee-days calculated correctly from roster, leave and punch data without manual correction. | E7: Employee-days requiring no correction / processed employee-days | F7: First-pass employee-days | G7: Processed employee-days | H7: % | I7: SBU / department / rule / period | J7: HR ISV attendance calculation | K7: Shows stability of attendance rules and upstream data. | L7: Increase | M7: Definition proposed
A8: M-A2P-07 | B8: Attendance Exception Rate | C8: Exception | D8: Share of processed employee-days with unresolved or material attendance exceptions. | E8: Employee-days with material exception / processed employee-days | F8: Exception employee-days | G8: Processed employee-days | H8: % | I8: Reason / site / SBU / period | J8: HR ISV exception queue | K8: Quantifies hidden HR/manager correction workload. | L8: Reduce preventable exceptions | M8: Definition proposed
A9: M-A2P-08 | B9: Missing Punch Rate | C9: Exception / Data Quality | D9: Share of expected clock events missing from the approved attendance source. | E9: Missing expected punch events / expected punch events | F9: Missing punch events | G9: Expected punch events | H9: % | I9: Site / device / department / employee type | J9: Attendance source + roster | K9: Separates device/behavior problems from payroll-engine issues. | L9: Reduce | M9: Definition proposed
A10: M-A2P-09 | B10: Attendance Correction Rate | C10: Human Dependency / Exception | D10: Share of processed employee-days requiring a correction request or authorized manual adjustment. | E10: Corrected employee-days / processed employee-days | F10: Corrected employee-days | G10: Processed employee-days | H10: % | I10: Reason / manager / site / SBU | J10: HR ISV correction workflow | K10: Measures manual intervention after digital capture. | L10: Reduce avoidable corrections | M10: Definition proposed
A11: M-A2P-10 | B11: Attendance Correction Cycle Time | C11: Process Performance | D11: Elapsed time from correction submission/detection to approved resolution. | E11: Average(correction resolution - request/detection timestamp) | F11: N/A | G11: N/A | H11: Hours | I11: Manager / department / reason | J11: HR ISV workflow | K11: Identifies approval bottlenecks before payroll cutoff. | L11: Reduce vs baseline | M11: Definition proposed
A12: M-A2P-11 | B12: Leave-to-Attendance Sync Rate | C12: Integration / Data Quality | D12: Share of approved leave days correctly reflected in attendance/payable-time classification without duplicate manual entry. | E12: Correctly synchronized approved leave days / approved leave days | F12: Synchronized leave days | G12: Approved leave days | H12: % | I12: Leave type / SBU / period | J12: HR ISV leave + attendance | K12: Verifies integrated time-off processing. | L12: Increase toward 100% | M12: Definition proposed
... A46: M-A2P-45 | B46: Payroll Processing Cost per Employee | C46: Business Value / Cost | D46: Normalized HR/payroll processing cost for the attendance-to-payroll cycle per payroll employee, using an approved cost model. | E46: Approved attributable A2P processing cost / payroll employees | F46: Approved attributable processing cost | G46: Payroll employees | H46: BDT / employee | I46: Company / SBU / period | J46: Time-cost model + HR/Finance data | K46: Tracks financial efficiency without confusing cost reduction with control reduction. | L46: Reduce vs normalized baseline where service/control outcomes are maintained | M46: Cost model requires validation

Sheet A2P Evidence Requirements
A1: Evidence ID | B1: Process Step / Area | C1: Evidence Level Supported | D1: Evidence Artifact | E1: System / Owner | F1: Required Fields | G1: Sampling Window / Frequency | H1: Validation Test | I1: Failure Signal | J1: Management Interpretation | K1: Source / URL | L1: Status
A2: EV-A2P-01 | B2: Entire A2P design baseline | C2: E1 | D2: Approved HR scope, process maps, payroll/attendance policies, fit-gap, workflow and integration design | E2: HR / AESL / Payroll Owner | F2: Scope, actors, policy rules, approval points, exceptions, integrations, system-of-record decisions | G2: Latest approved versions; review on material change | H2: Map every A2P L4-L6 step to approved requirement/process evidence | I2: Draft/conflicting process; open ownership; missing rule or integration decision | J2: Proves intended design only, not actual production maturity | K2: https://docs.google.com/spreadsheets/d/1XfHiOhLTJvGO_VKHyitZ8ijc_og8feRt5wAfyi8PC48/edit | L2: Available; detailed process evidence pending
A3: EV-A2P-02 | B3: Payroll population / employee eligibility | C3: E2-E4 | D3: Authoritative employee population and payroll inclusion/exclusion extract | E3: HR Master Data / Payroll | F3: Employee ID, company/SBU, employment status, join/exit dates, payroll eligibility, approved exclusion reason | G3: 3 consecutive payroll periods across representative SBUs | H3: Reconcile expected active/payroll population to actual payroll run and approved exclusions | I3: Missing active employee; unauthorized inclusion; untraceable exclusion | J3: Establishes whether payroll begins from a governed workforce population | K3: https://docs.google.com/spreadsheets/d/1XfHiOhLTJvGO_VKHyitZ8ijc_og8feRt5wAfyi8PC48/edit | L3: Pending production sample
A4: EV-A2P-03 | B4: Calendar / roster / shift | C4: E2-E4 | D4: Work calendar, holiday, shift and roster configuration plus assignment history | E4: HR Operations / HR ISV | F4: Employee/group, calendar, shift, roster dates, effective dates, change/approval history | G4: Current configuration + 60-90 days history | H4: Sample employees and reconstruct expected schedule used for attendance calculation | I4: Overlapping/missing roster; retrospective undocumented edit; wrong holiday/calendar | J4: Separates time-planning quality from device or payroll calculation issues | K4: https://docs.google.com/spreadsheets/d/1XfHiOhLTJvGO_VKHyitZ8ijc_og8feRt5wAfyi8PC48/edit | L4: Pending configuration/production evidence
A5: EV-A2P-04 | B5: Raw attendance capture | C5: E3-E4 | D5: Biometric/device/raw attendance event extract | E5: Attendance Device / HR Operations | F5: Employee/device ID, event type, timestamp, location/site, source sequence/id | G5: 30-60 days across representative sites/devices | H5: Check completeness, duplicates, timestamp integrity and employee/device mapping | I5: Paper/manual replacement; duplicate/missing events; unlinked employee identity | J5: Proves actual digital attendance capture rather than configured capability | K5: https://docs.google.com/spreadsheets/d/1XfHiOhLTJvGO_VKHyitZ8ijc_og8feRt5wAfyi8PC48/edit | L5: Pending device extract
A6: EV-A2P-05 | B6: Attendance integration | C6: E3-E4 | D6: Source-target interface logs, failed-record queue and reconciliation totals | E6: Technical Lead / HR ISV Integration | F6: Source count, target count, correlation ID, rejected record, retry, final status, timestamp | G6: 30 days; daily reconciliation | H6: Match device events to HR ISV ingestion and inspect failed/retried records | I6: Unreconciled count; silent failure; duplicate ingestion; manual file with no control | J6: Measures attendance-interface reliability and hidden manual fallback | K6: https://docs.google.com/spreadsheets/d/1XfHiOhLTJvGO_VKHyitZ8ijc_og8feRt5wAfyi8PC48/edit | L6: Pending interface evidence
A7: EV-A2P-06 | B7: Attendance calculation | C7: E3-E4 | D7: Calculated attendance records with source punches, roster and rule version | E7: HR Operations / HR ISV | F7: Employee/date, roster, punches, leave, status, payable time, late/early/absence result, rule version | G7: 2 payroll cycles; representative shifts | H7: Recalculate sample employee-days and compare system result to approved policy | I7: Unexplained manual status; inconsistent rule application; no source lineage | J7: Proves deterministic attendance processing quality | K7: https://docs.google.com/spreadsheets/d/1XfHiOhLTJvGO_VKHyitZ8ijc_og8feRt5wAfyi8PC48/edit | L7: Pending production evidence
A8: EV-A2P-07 | B8: Attendance exceptions | C8: E3-E4 | D8: Missing/invalid punch, roster conflict and attendance exception queue | E8: HR Operations | F8: Exception type, employee/date, source events, owner, opened/closed time, disposition | G8: 2 payroll cycles | H8: Verify material exceptions are detected, owned and resolved before certified close | I8: Payroll proceeds with material unresolved exceptions; no owner/SLA; free-text only | J8: Quantifies real manual exception burden | K8: https://docs.google.com/spreadsheets/d/1XfHiOhLTJvGO_VKHyitZ8ijc_og8feRt5wAfyi8PC48/edit | L8: Pending production evidence
A9: EV-A2P-08 | B9: Attendance correction workflow | C9: E3-E4 | D9: Correction request, before/after value, evidence and approval history | E9: HR Operations / Managers | F9: Employee/date, original value, requested value, reason, requester, approver, decision, timestamps | G9: 60-90 days; all material and sampled routine corrections | H9: Confirm original data is preserved and requester cannot approve own correction | I9: Direct overwrite; no reason; self-approval; correction outside workflow | J9: Measures correction governance and human dependency | K9: https://docs.google.com/spreadsheets/d/1XfHiOhLTJvGO_VKHyitZ8ijc_og8feRt5wAfyi8PC48/edit | L9: Pending workflow evidence
A10: EV-A2P-09 | B10: Leave-to-attendance | C10: E3-E4 | D10: Approved leave records joined to attendance outcome and leave balance | E10: HR Operations / HR ISV | F10: Leave ID/type, dates, approval, balance effect, attendance classification | G10: 2 payroll cycles | H10: Sample approved leave and verify no duplicate manual attendance input and correct balance/status | I10: Approved leave not reflected; manual duplicate entry; inconsistent balance | J10: Proves integration between leave and attendance | K10: https://docs.google.com/spreadsheets/d/1XfHiOhLTJvGO_VKHyitZ8ijc_og8feRt5wAfyi8PC48/edit | L10: Pending production evidence
A11: EV-A2P-10 | B11: Overtime calculation & approval | C11: E3-E4 | D11: Calculated OT, policy/rate basis and approval workflow | E11: HR Operations / Payroll | F11: Employee/date, attendance hours, eligible OT hours, rule/rate, approval, approver, timestamps | G11: 2 payroll cycles; include exception cases | H11: Recalculate sampled OT and trace approved result to payroll input | I11: Spreadsheet calculation; no approval; OT paid differs from approved OT | J11: Establishes payable-time automation and approval control | K11: https://docs.google.com/spreadsheets/d/1XfHiOhLTJvGO_VKHyitZ8ijc_og8feRt5wAfyi8PC48/edit | L11: Pending production evidence
A12: EV-A2P-11 | B12: Attendance close / lock | C12: E3-E4 | D12: Attendance close certification, control totals and reopen history | E12: HR Operations | F12: Period, employee counts, exception count, close time, approver, reopen reason/user/time | G12: 3 payroll periods | H12: Verify no uncontrolled changes after close and all reopenings are authorized | I12: Post-close edits without audit; frequent late reopen; unresolved exceptions at close | J12: Shows upstream readiness and cutoff discipline | K12: https://docs.google.com/spreadsheets/d/1XfHiOhLTJvGO_VKHyitZ8ijc_og8feRt5wAfyi8PC48/edit | L12: Pending production evidence
... A30: EV-A2P-29 | B30: Transformation outcome verification | C30: E5 | D30: Approved baseline-vs-post-change payroll KPI and benefit pack | E30: HR Process Owner / Finance / Transformation Office | F30: Baseline/post period, normalized headcount/scope, accuracy, cycle time, human minutes, payment/posting outcomes, cost, adoption, control results, assumptions | G30: Per initiative; 30/60/90-day post-go-live and quarterly thereafter | H30: Verify comparable population/scope, attributable change, no control degradation and HR/Finance sign-off | I30: Claimed savings without baseline; headcount/scope distortion; weaker accuracy/control; adoption not sustained | J30: Only E5 should be treated as verified realized A2P transformation value | K30: https://learn.microsoft.com/en-us/power-automate/process-mining-overview | L30: Not available yet

Sheet Wave5 P2P Process Tree
A1: Process Step ID | B1: L2 Functional Wing | C1: L3 Process Group | D1: L4 Sub-process | E1: L5 Activity | F1: L6 Task / Decision | G1: Primary System | H1: System of Record | I1: Human Role | J1: Automation Mode | K1: Current State | L1: Target State | M1: Required Control | N1: Primary KPI | O1: Evidence Needed | P1: Source Title | Q1: Source URL | R1: Calibration Status
A2: P2P-001 | B2: Sales / Planning / Production | C2: Demand & Production Planning | D2: Demand Signal Consolidation | E2: Consolidate production demand | F2: Consolidate sales orders, forecast, inventory position and approved production requirements into a dated production demand view. | G2: Business Central Planning + Sales/Forecast Source | H2: Business Central planning demand | I2: Production Planner | J2: Rules + human planning review | K2: Candidate S0-S1 | L2: S2/S3 | M2: Approved demand sources; duplicate demand prevention; demand-source traceability | N2: Demand-to-plan conversion rate | O2: Demand source, quantity, due date, source reference, planning timestamp | P2: Production BRD + Microsoft BC Planning | Q2: https://learn.microsoft.com/en-us/dynamics365/business-central/production-about-planning-functionality | R2: Not calibrated
A3: P2P-002 | B3: Planning / Production | C3: Demand & Production Planning | D3: Net Requirements Planning | E3: Calculate production requirements | F3: Calculate net requirements using demand, inventory, replenishment policy, BOM structure and lead times to propose production supply. | G3: Business Central Planning Worksheet | H3: Business Central | I3: Production Planner | J3: Deterministic planning engine + human review | K3: Candidate S0-S1 | L3: S2 | M3: Approved planning parameters; no untraceable manual quantity changes; planning warnings reviewed | N3: Planning recommendation acceptance rate | O3: Planning worksheet lines, source demand, action message, planner decision | P3: Microsoft BC Planning | Q3: https://learn.microsoft.com/en-us/dynamics365/business-central/production-about-planning-functionality | R3: Not calibrated
A4: P2P-003 | B4: Planning / Production | C4: Demand & Production Planning | D4: Production Plan Approval | E4: Approve production plan | F4: Review proposed quantities, due dates, capacity constraints and material risks before committing firm/released production orders. | G4: Business Central + Approved Planning Workflow | H4: Approved production plan / production orders | I4: Production Manager / Planner | J4: Human approval with system evidence | K4: Candidate S0-S1 | L4: S2 | M4: Defined authority; version history; exceptions and overrides documented | N4: Production plan approval cycle time | O4: Plan version, approvals, constraints, changes, timestamps | P4: Production BRD | Q4: https://docs.google.com/document/d/1JZeibH6jDWNLybYCgJMq-fEYwidL32H4_BTkQFD0Ozw/edit | R4: Not calibrated
A5: P2P-004 | B5: Production | C5: Manufacturing Master Data | D5: Production BOM / Recipe | E5: Validate certified BOM/recipe | F5: Maintain approved component quantities, versions and effective dates for the product/grade before production execution. | G5: Business Central Production BOM | H5: Business Central | I5: Production Engineering / Authorized Master Data | J5: Controlled master maintenance | K5: Candidate S0-S1 | L5: S2 | M5: Certified/approved BOM; effective dates; version/change control; segregation from production posting | N5: BOM master completeness | O5: BOM version, components, quantities, approval/certification, effective dates | P5: Production BRD + Microsoft BC Manufacturing Setup | Q5: https://learn.microsoft.com/en-us/dynamics365/business-central/production-configure-production-processes | R5: Not calibrated
A6: P2P-005 | B6: Production | C6: Manufacturing Master Data | D6: Routing | E6: Validate production route | F6: Maintain ordered operations, work/machine centers, setup/run/wait/move times and routing versions for each manufactured item/variant. | G6: Business Central Routings | H6: Business Central | I6: Production Engineering | J6: Controlled master maintenance | K6: Candidate S0-S1 | L6: S2 | M6: Approved routing; effective dates; operation sequence; valid resource assignment | N6: Routing master completeness | O6: Routing version, operation numbers, centers, times, approval/certification | P6: Microsoft BC Manufacturing Setup | Q6: https://learn.microsoft.com/en-us/dynamics365/business-central/production-configure-production-processes | R6: Not calibrated
A7: P2P-006 | B7: Production / QC | C7: Manufacturing Master Data | D7: Product & Quality Specification | E7: Maintain grade/specification standards | F7: Maintain product grade/category, chemistry or formulation targets, dimensional/mechanical tolerances, test requirements and applicable quality standards. | G7: Quality Management + Item/Specification Master | H7: Approved quality specification | I7: Quality / R&D / Authorized Master Data | J7: Controlled master maintenance | K7: Candidate S0-S1 | L7: S2 | M7: Versioned standards; effective dates; instrument/test mapping; independent approval | N7: Quality specification completeness | O7: Grade, target limits, test plan, standard, version, approval | P7: Production Module Data Record - AIL | Q7: https://docs.google.com/spreadsheets/d/1VsC-rDy7XjB-_T2TIvw1F7HsHZ3bJwqTPLn67xD0pMM/edit | R7: Not calibrated
A8: P2P-007 | B8: Production | C8: Capacity & Scheduling | D8: Work/Machine Center Readiness | E8: Maintain production resources | F8: Maintain work centers, machine centers, calendars, capacity, efficiency, costs and constrained-resource settings used for scheduling. | G8: Business Central Work/Machine Centers | H8: Business Central | I8: Production Planner / Engineering | J8: Configured capacity model | K8: Candidate S0-S1 | L8: S2 | M8: Approved calendars/capacity; effective maintenance windows; valid cost/resource assignment | N8: Capacity master readiness | O8: Calendar, capacity, efficiency, machine/work center, cost and availability | P8: Microsoft BC Work/Machine Centers | Q8: https://learn.microsoft.com/en-us/dynamics365/business-central/production-how-to-set-up-work-and-machine-centers | R8: Not calibrated
A9: P2P-008 | B9: Planning / Production | C9: Capacity & Scheduling | D9: Load & Capacity Review | E9: Review planned load | F9: Compare planned/released operation load against available work/machine-center capacity and identify overload or idle capacity. | G9: Business Central Capacity / Load | H9: Business Central | I9: Production Planner | J9: Deterministic calculation + human review | K9: Candidate S0-S1 | L9: S2/S3 | M9: Current calendar/capacity basis; overload exception recorded; no hidden off-system capacity | N9: Capacity utilization / overload rate | O9: Center capacity, load, scheduled operations, overload periods | P9: Microsoft BC Capacity Planning | Q9: https://learn.microsoft.com/en-us/dynamics365/business-central/production-how-to-view-the-load-on-work-centers | R9: Not calibrated
A10: P2P-009 | B10: Planning / Production | C10: Capacity & Scheduling | D10: Operation Scheduling | E10: Schedule production operations | F10: Schedule production order routing operations against work/machine centers using due date, operation sequence, capacity and queue/setup/run times. | G10: Business Central Production Scheduling | H10: Business Central | I10: Production Planner | J10: Scheduling engine + human exception handling | K10: Candidate S0-S1 | L10: S2/S3 | M10: No operation overlap beyond valid concurrency; constrained-resource rules respected; reschedule reason retained | N10: Schedule adherence | O10: Planned start/end, actual start/end, center, reschedule reason | P10: Microsoft BC Production Orders / Capacity | Q10: https://learn.microsoft.com/en-us/dynamics365/business-central/production-about-production-orders | R10: Not calibrated
A11: P2P-010 | B11: Production | C11: Production Order Management | D11: Production Order Creation | E11: Create production order | F11: Create firm planned/released production order from approved demand with item, quantity, due date, BOM, routing and location references. | G11: Business Central Production Orders | H11: Business Central | I11: Planner / System | J11: System generation + human review | K11: Candidate S0-S1 | L11: S2 | M11: Trace to source demand; valid BOM/routing; no duplicate order; approved quantity/due date | N11: Production order auto-generation rate | O11: Prod. order, source demand, item, qty, due date, BOM/routing, created by/time | P11: Microsoft BC Production Orders | Q11: https://learn.microsoft.com/en-us/dynamics365/business-central/production-about-production-orders | R11: Not calibrated
A12: P2P-011 | B12: Production | C12: Production Order Management | D12: Production Order Refresh & Validation | E12: Refresh components/routing | F12: Refresh production order to current approved BOM/routing and validate components, operations, flushing methods and output method before release. | G12: Business Central Production Order | H12: Business Central | I12: Planner / Production Controller | J12: Deterministic validation | K12: Candidate S0-S1 | L12: S2 | M12: Approved master-data version; change impact visible; no silent refresh after execution starts | N12: Production order readiness pass rate | O12: Order version, components, routing, warnings/errors, refresh timestamp | P12: Microsoft BC Production Orders | Q12: https://learn.microsoft.com/en-us/dynamics365/business-central/production-about-production-orders | R12: Not calibrated
... A43: P2P-042 | B43: Production / Finance - AIL Variant | C43: AIL Production Economics | D43: Energy, Yield & Loss Analysis | E43: Analyze heat/mill efficiency | F43: Measure energy consumption, metallic yield, burning loss, slag, end-cut, mill scale and other production losses by heat/order/period. | G43: Production Data + Business Central + BI | H43: Verified production/inventory/cost events | I43: Production Manager / Finance / Energy Analyst | J43: Analytics; future AI recommendation only | K43: Candidate S0 | L43: S3 | M43: Meter/source lineage; loss taxonomy; quantity/value reconciliation; no autonomous process-control action | N43: Energy per ton / metallic yield / loss rate | O43: Heat/order energy, input weight, output weight, loss categories, by-product recovery, cost | P43: AIL Production BRD + Report Analysis | Q43: https://docs.google.com/document/d/1JZeibH6jDWNLybYCgJMq-fEYwidL32H4_BTkQFD0Ozw/edit | R43: Not calibrated

Sheet P2P Metric Dictionary
A1: Metric ID | B1: Metric Name | C1: KPI Family | D1: Definition | E1: Formula / Calculation | F1: Numerator | G1: Denominator | H1: Unit | I1: Grain | J1: Source Event / System | K1: Management Use | L1: Proposed Direction / Target | M1: Status
A2: M-P2P-01 | B2: Plan-to-Produce End-to-End Cycle Time | C2: Process Performance | D2: Elapsed time from approved production demand/plan release to accepted finished-goods receipt and production-order completion. | E2: Average(FG accepted/production complete timestamp - approved plan/demand timestamp) | F2: N/A | G2: N/A | H2: Hours / days | I2: Production order / product / SBU | J2: Planning + production + inventory events | K2: Primary end-to-end manufacturing responsiveness measure. | L2: Reduce vs verified baseline while maintaining quality/safety | M2: Definition proposed
A3: M-P2P-02 | B3: Demand-to-Plan Conversion Rate | C3: Planning | D3: Share of eligible production demand represented in an approved production plan/order without off-system omission. | E3: Demand qty covered by approved production plan / eligible production demand qty | F3: Demand qty covered by plan | G3: Eligible production demand qty | H3: % | I3: Product / SBU / period | J3: Sales/forecast demand + BC planning | K3: Shows whether production planning reflects the true demand picture. | L3: Increase toward approved coverage policy | M3: Definition proposed
A4: M-P2P-03 | B4: Planning Recommendation Acceptance Rate | C4: Automation / Planning | D4: Share of system planning recommendations accepted without material manual quantity/date change. | E4: Accepted recommendations / actionable recommendations | F4: Accepted recommendations | G4: Actionable recommendations | H4: % | I4: Planner / item / SBU | J4: BC planning worksheet/action messages | K4: Indicates planning-parameter quality and readiness for higher automation. | L4: Increase where planning inputs are stable | M4: Definition proposed
A5: M-P2P-04 | B5: Production Plan Approval Cycle Time | C5: Process Performance | D5: Elapsed time from plan submission to approved/committed production plan. | E5: Average(approval timestamp - submission timestamp) | F5: N/A | G5: N/A | H5: Hours | I5: Plan / SBU | J5: Planning approval/version history | K5: Shows planning-governance delay before execution. | L5: Reduce vs baseline | M5: Definition proposed
A6: M-P2P-05 | B6: BOM Master Completeness | C6: Master Data | D6: Share of active manufactured items with approved/certified BOM or recipe, effective version and complete component data. | E6: Active manufactured items with complete approved BOM / active manufactured items | F6: Complete approved BOM items | G6: Active manufactured items | H6: % | I6: Item / SBU | J6: BC Production BOM / recipe master | K6: Foundation measure for reliable planning and consumption. | L6: Increase toward 100% for active manufactured items | M6: Definition proposed
A7: M-P2P-06 | B7: Routing Master Completeness | C7: Master Data | D7: Share of active manufactured items with approved routing covering required operations and valid resources. | E7: Items with complete approved routing / active manufactured items requiring routing | F7: Complete approved routing items | G7: Items requiring routing | H7: % | I7: Item / SBU | J7: BC routings | K7: Foundation measure for scheduling, capacity and shop-floor traceability. | L7: Increase toward 100% where routing is required | M7: Definition proposed
A8: M-P2P-07 | B8: Quality Specification Completeness | C8: Master Data / Quality | D8: Share of active products/grades with approved quality limits, test plan and effective specification. | E8: Products with complete approved quality specification / active products requiring QC | F8: Complete quality-spec products | G8: Active products requiring QC | H8: % | I8: Product / grade / SBU | J8: Quality/specification master | K8: Precondition for deterministic QC and controlled release. | L8: Increase toward 100% | M8: Definition proposed
A9: M-P2P-08 | B9: Capacity Master Readiness | C9: Master Data / Capacity | D9: Share of active work/machine centers with valid calendar, capacity, efficiency and required cost/resource settings. | E9: Ready centers / active centers | F9: Ready centers | G9: Active centers | H9: % | I9: Center / plant | J9: BC work/machine center master | K9: Determines whether scheduling and capacity metrics can be trusted. | L9: Increase toward 100% | M9: Definition proposed
A10: M-P2P-09 | B10: Capacity Utilization | C10: Efficiency / Capacity | D10: Scheduled/actual productive load relative to available practical capacity for comparable centers. | E10: Productive load hours / available practical capacity hours | F10: Productive load hours | G10: Available capacity hours | H10: % | I10: Work/machine center / shift / period | J10: BC capacity/load + actual output time | K10: Supports capacity balancing and bottleneck analysis. | L10: Optimize by center; not simply maximize | M10: Definition proposed
A11: M-P2P-10 | B11: Capacity Overload Rate | C11: Exception / Planning | D11: Share of scheduled center-periods where planned load exceeds available approved capacity. | E11: Overloaded center-periods / scheduled center-periods | F11: Overloaded periods | G11: Scheduled center-periods | H11: % | I11: Center / day / shift | J11: BC capacity planning | K11: Shows infeasible schedules and capacity-planning quality. | L11: Reduce avoidable overload | M11: Definition proposed
A12: M-P2P-11 | B12: Schedule Adherence | C12: Execution | D12: Share of operations/orders starting and finishing within approved scheduling tolerance. | E12: Operations/orders within tolerance / completed scheduled operations/orders | F12: Within-tolerance operations/orders | G12: Completed scheduled operations/orders | H12: % | I12: Order / operation / plant | J12: Planned vs actual production events | K12: Primary production execution reliability indicator. | L12: Increase | M12: Definition proposed
... A46: M-P2P-45 | B46: AIL Metallic Yield | C46: AIL Variant / Yield | D46: Accepted billet/finished metallic output relative to verified metallic input for the selected production stage. | E46: Accepted metallic output weight / verified metallic input weight | F46: Accepted metallic output | G46: Verified metallic input | H46: % | I46: Heat / grade / furnace / period | J46: Heat charge + billet/FG output + loss records | K46: Core AIL yield/loss management metric. | L46: Increase within approved metallurgical/process limits | M46: Requires verified liquid-metal/output measurement basis

Sheet P2P Evidence Requirements
A1: Evidence ID | B1: Process Step / Area | C1: Evidence Level Supported | D1: Evidence Artifact | E1: System / Owner | F1: Required Fields | G1: Sampling Window / Frequency | H1: Validation Test | I1: Failure Signal | J1: Management Interpretation | K1: Source / URL | L1: Status
A2: EV-P2P-01 | B2: Entire P2P design baseline | C2: E1 | D2: Approved production BRD/SDD, process maps, production master-data design, QC design and organization variants | E2: Production / AESL / Process Owner | F2: Scope, process stages, actors, master data, rules, controls, integrations, variants, target behavior | G2: Latest approved versions; review on material change | H2: Map every P2P L4-L6 step to approved requirement/process evidence and identify unsupported assumptions | I2: Draft/conflicting process; missing organization variant; unclear owner/control | J2: Proves intended process only, not live manufacturing maturity | K2: https://docs.google.com/document/d/1JZeibH6jDWNLybYCgJMq-fEYwidL32H4_BTkQFD0Ozw/edit | L2: Available; evidence mapping pending
A3: EV-P2P-02 | B3: Demand / production plan | C3: E2-E4 | D3: Production demand, planning worksheet/action messages, approved plan and production-order creation source | E3: Planning / Business Central | F3: Demand source, item, quantity, due date, inventory basis, action message, planner decision, approval, production-order reference | G3: 8-12 weeks across representative product families/SBUs | H3: Trace demand through planning recommendation to approved order and sample rejected/changed recommendations | I3: Spreadsheet-only plan; no source reference; unexplained manual quantity/date change | J3: Establishes actual planning digitization and recommendation quality | K3: https://learn.microsoft.com/en-us/dynamics365/business-central/production-about-planning-functionality | L3: Pending production planning sample
A4: EV-P2P-03 | B4: Production BOM / recipe | C4: E2-E4 | D4: Approved BOM/recipe versions and change history | E4: Production Engineering / Master Data | F4: Item/grade, version, components, qty/UOM, effective dates, approval/certification, changed by/time | G4: Current active master + 90-day change history | H4: Sample active products and verify production orders reference valid approved versions | I4: Unapproved BOM; outdated component qty; production order using wrong version | J4: Foundation evidence for material planning/consumption integrity | K4: https://learn.microsoft.com/en-us/dynamics365/business-central/production-configure-production-processes | L4: Pending master-data extract
A5: EV-P2P-04 | B5: Routing / operations | C5: E2-E4 | D5: Approved routing versions and operation/resource assignments | E5: Production Engineering | F5: Item/variant, routing version, operation sequence, work/machine centers, times, effective dates, approval | G5: Current active master + 90-day change history | H5: Sample products and verify executed orders/operations follow approved routing or documented deviation | I5: Missing operation; invalid resource; undocumented route bypass | J5: Determines scheduling and process-traceability readiness | K5: https://learn.microsoft.com/en-us/dynamics365/business-central/production-configure-production-processes | L5: Pending routing extract
A6: EV-P2P-05 | B6: Quality specification / test plan | C6: E2-E4 | D6: Approved product/grade specifications, inspection templates and effective test limits | E6: Quality / R&D | F6: Product/grade, parameter/test, lower/upper limits, sampling requirement, standard/version, approval/effective date | G6: Current active specs + 90-day changes | H6: Trace sampled production inspections to the correct effective specification | I6: Free-text limits; outdated spec; test result not tied to version | J6: Foundation for governed digital QC | K6: https://learn.microsoft.com/en-us/dynamics365/business-central/qms-overview | L6: Pending quality master evidence
A7: EV-P2P-06 | B7: Work/machine center capacity | C7: E2-E4 | D7: Work/machine center master, calendars, capacity, efficiency, cost and downtime/availability basis | E7: Production Planning / Engineering | F7: Center ID, calendar, capacity, efficiency, cost, active dates, maintenance/availability blocks | G7: Current master + 8-12 week schedule history | H7: Recalculate available capacity for sampled periods and compare to planned load | I7: Stale calendar; missing capacity; off-system capacity adjustment | J7: Determines whether scheduling/utilization KPIs are trustworthy | K7: https://learn.microsoft.com/en-us/dynamics365/business-central/production-how-to-set-up-work-and-machine-centers | L7: Pending capacity evidence
A8: EV-P2P-07 | B8: Production order creation / release | C8: E3-E4 | D8: Production-order lifecycle/status history with source demand and readiness controls | E8: Business Central / Production Control | F8: Order no., source, item, qty, due date, BOM/routing, Created/Firm Planned/Released/Finished status events, user/time, exceptions | G8: 60-90 days across active plants | H8: Trace order from source demand to release and verify readiness/approval evidence | I8: Manual orphan order; release with missing master/material control; backdated status | J8: Core evidence of governed planning-to-execution transition | K8: https://learn.microsoft.com/en-us/dynamics365/business-central/production-about-production-orders | L8: Pending production-order extract
A9: EV-P2P-08 | B9: Material availability & reservation | C9: E3-E4 | D9: Production component demand, inventory availability and reservation entries | E9: Inventory / Business Central | F9: Order, component, required qty, on-hand, available, reserved, location, shortage, reservation/release events | G9: 60-90 days; include shortage/cancellation cases | H9: Trace sample orders from requirement through reservation and actual issue | I9: Duplicate allocation; unexplained negative availability; stale reservation | J9: Measures material-readiness control before shop-floor release | K9: https://learn.microsoft.com/en-us/dynamics365/business-central/production-manage-manufacturing | L9: Pending inventory/production extract
A10: EV-P2P-09 | B10: Production material staging / pick | C10: E3-E4 | D10: Warehouse/production pick and staging documents linked to released production order | E10: Warehouse / Production | F10: Order, component, lot/bin/location, requested/handled qty, short-pick reason, worker, timestamps | G10: 30-60 days across representative warehouses/plants | H10: Trace staged material to production order and subsequent consumption | I10: Paper-only staging; no lot/bin trace; staged qty not tied to order | J10: Shows warehouse-to-production digital handoff quality | K10: https://learn.microsoft.com/en-us/dynamics365/business-central/production-how-to-set-up-work-and-machine-centers | L10: Pending staging evidence
A11: EV-P2P-10 | B11: Material consumption | C11: E3-E4 | D11: Expected and actual production consumption with flushing method and source lot | E11: Production / Inventory | F11: Order, component, expected qty, actual qty, UOM, lot/location, operation, flushing method, posting user/time | G11: 60-90 days; representative products | H11: Recalculate consumption variance and verify automated flushing is configured/used as designed | I11: Manual rekey; unexplained excess use; missing lot/order linkage | J11: Core evidence for material efficiency and production costing | K11: https://learn.microsoft.com/en-us/dynamics365/business-central/production-manage-manufacturing | L11: Pending consumption extract
A12: EV-P2P-11 | B12: Operation start/end & progress | C12: E3-E4 | D12: Actual operation events by production order/routing operation/resource | E12: Production / Shop Floor | F12: Order, operation, work/machine center, operator/shift, planned/actual start/end, output/time, status | G12: 30-60 days by plant/shift | H12: Compare actual events to routing/schedule and identify retrospective/manual-only reporting | I12: No operation timestamps; end-of-shift batch entry; resource mismatch | J12: Determines actual WIP visibility and schedule-adherence evidence | K12: https://learn.microsoft.com/en-us/dynamics365/business-central/production-about-production-orders | L12: Pending shop-floor events
... A33: EV-P2P-32 | B33: Transformation outcome verification | C33: E5 | D33: Approved baseline-vs-post-change manufacturing KPI and benefit pack | E33: Production Process Owner / Finance / Quality / Transformation Office | F33: Baseline/post period, normalized product mix/volume, cycle time, yield, scrap, energy, cost, quality, human effort, adoption, controls, assumptions | G33: Per initiative; 30/60/90-day post-go-live and quarterly thereafter | H33: Verify comparable product/process scope, attributable change, no safety/quality/control degradation and owner/Finance sign-off | I33: Claimed savings without baseline; mix distortion; quality or safety degradation; benefit not sustained | J33: Only E5 should be treated as verified realized production transformation value | K33: https://learn.microsoft.com/en-us/power-automate/process-mining-overview | L33: Not available yet

Sheet O2C Calibration Register
A1: Calibration ID | B1: Process Segment | C1: Process Step IDs | D1: Provisional Current State | E1: Provisional Evidence Level | F1: Confidence | G1: Evidence Basis | H1: Supporting Evidence | I1: Observed Gap / Blocker | J1: Live Evidence Required | K1: Promotion Gate | L1: Recommended Target | M1: Calibration Status | N1: Last Reviewed
A2: CAL-O2C-01 | B2: Customer onboarding, ERP creation & approval | C2: O2C-001:003 | D2: S1-S2 | E2: E1-E2 Candidate | F2: Medium | G2: Sales Eco/BC design and active QA evidence support a governed digital flow, but not sustained production use. | H2: BSES-1331 QA In Review; Sales Eco↔BC solution design | I2: Production creation success, approval throughput, duplicate/error and unblock behavior not sampled. | J2: Customer-create API logs; BC customer status history; approval entries; error/retry logs; 30-day sample. | K2: E3 only after real production customers traverse create→approve/reject with traceable events; E4 requires cycle/adoption/error metrics. | L2: S2 | M2: Provisional evidence review complete; live execution pending | N2: 2026-09-14
A3: CAL-O2C-02 | B3: Pricing & discount governance | C3: O2C-004,O2C-008 | D3: S1-S2 | E3: E1-E2 Candidate | F3: Medium | G3: Primary Sales design defines governed pricing, effective dates and exception approval. | H3: Primary Sales updated SDD/process mapping | I3: Actual approval volume, overrides and off-system price handling are not evidenced. | J3: Price versions; approval logs; price source on orders; discount override events. | K3: E3 requires live price/discount decisions; E4 requires approval-cycle and exception-rate measures. | L3: S2 | M3: Production evidence pending | N3: 2026-09-14
A4: CAL-O2C-03 | B4: Customer Order intake & ERP Sales Order creation | C4: O2C-005 | D4: S1-S2 | E4: E2 Candidate | F4: High | G4: Recent Jira shows active delivered/QA capability around Customer Order and status correction. | H4: BSES-1336 QA In Review; BSES-1411 Done; BSES-2719 Done | I4: No verified production CO→SO conversion rate, cycle time, failures or human-touch count. | J4: CO submit; correlation ID; SO creation; user/system action events; retries/errors. | K4: E3 requires successful live CO→SO chains; E4 requires STP, cycle-time and failure metrics. | L4: S2 | M4: Live chain extraction pending | N4: 2026-09-14
A5: CAL-O2C-04 | B5: Credit eligibility & exception approval | C5: O2C-006:007 | D5: S1-S2 with S2 rule pockets | E5: E1-E2 Candidate | F5: Medium | G5: Finance/ERP design specifies deterministic credit checks and governed exception approval. | H5: Finance SDD; Sales/Logistics design | I5: Consistent enforcement, auto-clear share and override reasons not measured. | J5: Credit limit; exposure; check result; approval event; override reason; approver/time. | K5: E3 requires production rule/approval events; E4 requires auto-clear, exception and cycle metrics. | L5: S2 | M5: Rule execution evidence pending | N5: 2026-09-14
A6: CAL-O2C-05 | B6: Inventory availability & reservation | C6: O2C-009:010 | D6: S1-S2 | E6: E1-E2 Candidate | F6: Medium | G6: BC/logistics design defines availability, location and reservation controls. | H6: Logistics SDD + BC inventory design | I6: Availability-pass rate, reservation automation and manual allocation not measured. | J6: Availability snapshots; reservation create/release events; source location; overrides. | K6: E3 requires live availability/reservation events; E4 requires pass/automation metrics. | L6: S2 | M6: Inventory event extraction pending | N6: 2026-09-14
A7: CAL-O2C-06 | B7: SO→DO fulfilment planning & loading preparation | C7: O2C-011:015 | D7: S1-S2 with delivered S2 components | E7: E2 Candidate | F7: High | G7: Jira shows optimization delivered, with performance and backlog-quantity items still open/in review. | H7: BSES-3057 Done; BSES-2941 In Review; BSES-2928 To Do; BSES-2923 Done | I7: Feature completion does not prove SO→DO STP, partial fulfillment, source override or cycle performance. | J7: SO-ready event; DO creation; parent refs; backlog qty; source; loading advice; manual allocation actions. | K7: E3 requires real SO→DO→loading chains; E4 requires cycle/partial/manual-touch measures. | L7: S2/S3 | M7: Production chain metrics pending | N7: 2026-09-14
A8: CAL-O2C-07 | B8: Loading, gate & dispatch execution | C8: O2C-016:018 | D8: Mixed S0-S1 | E8: E1-E2 Candidate | F8: Low-Medium | G8: Detailed logistics target process exists, but direct production telemetry is not verified. | H8: Logistics SDD/PRD | I8: Digital capture coverage for load, gate and dispatch and manual bypass is unknown. | J8: Load confirmation; discrepancy; gate-in/out; dispatch; vehicle/driver; user/device timestamps. | K8: E3 requires production execution records; E4 requires dwell/on-time/adoption metrics. | L8: S2 | M8: Field execution calibration required | N8: 2026-09-14
A9: CAL-O2C-08 | B9: POD & delivery exception handling | C9: O2C-019:020 | D9: Mixed S0-S1 | E9: E1-E2 Candidate | F9: Low-Medium | G9: Logistics design defines POD and exception evidence, but live capture is unverified. | H9: Logistics SDD/PRD | I9: POD completeness and shortage/damage/rejection handling are unknown. | J9: POD; recipient/time; delivered qty; exception code; return/recovery action; undelivered balance. | K9: E3 requires live POD/exception events; E4 requires capture and exception-rate metrics. | L9: S2 | M9: Production POD sample pending | N9: 2026-09-14
A10: CAL-O2C-09 | B10: Invoice generation & validation | C10: O2C-021:022 | D10: S1-S2 | E10: E2 Candidate | F10: Medium-High | G10: BC finance design supports posting; invoice synchronization remains under QA. | H10: BSES-1538 QA In Review; Finance SDD | I10: Delivery→invoice latency, accuracy, reversal/correction and sync reliability need measurement. | J10: Shipment/DN ref; invoice post time; GL entries; corrections/reversals; sync request/response. | K10: E3 requires posted live invoices linked to delivery; E4 requires latency/accuracy/failure measures. | L10: S2 | M10: Invoice production sample pending | N10: 2026-09-14
A11: CAL-O2C-10 | B11: Payment collection & application | C11: O2C-023:024 | D11: S1-S2 | E11: E2 Candidate | F11: Medium | G11: Finance design supports receipt/application; MR bank/subbranch sync remains under QA. | H11: BSES-1792 QA In Review; Finance SDD | I11: Digital receipt coverage, first-pass match, unapplied cash and off-system receipts not measured. | J11: MR/receipt; bank ref; BC posting; application; unapplied balance; sync/error logs. | K11: E3 requires live receipt/application records; E4 requires digital-receipt and auto-application metrics. | L11: S2/S3 | M11: Payment event extraction pending | N11: 2026-09-14
A12: CAL-O2C-11 | B12: Collections, aging & recovery | C12: O2C-025 | D12: Underlying S1-S2; management layer S0-S1 | E12: E1-E2 Candidate | F12: High | G12: BC aging capability exists by design, but E19 collection/recovery management layer is not delivered. | H12: BSES-2973,2974,2975,2976,2977,2980,2981,2982,2983,2984,2985,2986,2987 all To Do | I12: No unified authoritative collection service/reconciliation or measured recovery workflow. | J12: Open AR; due date; NOD commitment; collection actions; MR/payment link; authoritative reconciliation. | K12: E3 requires production collection/recovery events; E4 requires DSO/overdue/NOD/recovery metrics. | L12: S3 decision support with controlled human action | M12: Foundation present; management layer pending | N12: 2026-09-14
... A15: CAL-O2C-14 | B15: End-to-end O2C performance intelligence | C15: O2C-029 | D15: Early S1 / TBD | E15: E1 | F15: High | G15: Metric architecture is defined, but no unified production event log has been extracted. | H15: Microsoft process-mining requirements + O2C metric dictionary | I15: No canonical live case/event model, variant analysis or human-touch classification. | J15: Unified event log: Case ID, Activity, Timestamp, source, actor/resource, document refs, execution type, exception/approval attributes. | K15: E3 begins when real cases are reconstructed; E4 requires repeatable refreshed metrics and variants. | L15: S3 | M15: Architecture ready; event extraction not started | N15: 2026-09-14

Sheet O2C Event Schema
A1: Field ID | B1: Field Name | C1: Requirement | D1: Level | E1: Data Type | F1: Definition | G1: Source Candidate | H1: Process-Mining / KPI Use | I1: Control / Evidence Use | J1: Reference URL
A2: EVT-001 | B2: Case_ID | C2: Core required | D2: Case | E2: String | F2: Canonical identifier for one end-to-end O2C case; use native chain ID where possible or a governed cross-reference key. | G2: Fabric mapping across Sales Eco, BC and Logistics | H2: Groups all events into one process instance. | I2: Prevents fragmented analysis of the same transaction. | J2: https://learn.microsoft.com/en-us/power-automate/process-mining-processes-and-data
A3: EVT-002 | B3: Event_ID | C3: AGI required | D3: Event | E3: String | F3: Unique immutable identifier for each event row. | G3: Source event ID or governed generated key | H3: Deduplication and event-level traceability. | I3: Supports auditability and repeatable reloads. | J3: https://learn.microsoft.com/en-us/power-automate/process-mining-normalized-import-authoring-guide
A4: EVT-003 | B4: Activity_Name | C4: Core required | D4: Event | E4: String | F4: Normalized activity such as CO Submitted, Credit Approved, SO Created, DO Created, POD Captured, Invoice Posted, Payment Applied. | G4: Mapped from source action/status/event | H4: Required process-mining activity field and variant analysis. | I4: Provides one enterprise process vocabulary. | J4: https://learn.microsoft.com/en-us/power-automate/process-mining-processes-and-data
A5: EVT-004 | B5: Event_Timestamp | C5: Core required | D5: Event | E5: Datetime | F5: Authoritative time at which the event occurred. | G5: Created/posted/approved/status-change timestamp | H5: Sequence and cycle-time analysis. | I5: Evidence chronology and SLA testing. | J5: https://learn.microsoft.com/en-us/power-automate/process-mining-processes-and-data
A6: EVT-005 | B6: Start_Timestamp | C6: Recommended | D6: Event | E6: Datetime | F6: Start of an activity when active duration can be measured. | G6: Workflow/task start | H6: Active processing-time analysis. | I6: Separates active effort from waiting. | J6: https://learn.microsoft.com/en-us/power-automate/process-mining-processes-and-data
A7: EVT-006 | B7: End_Timestamp | C7: Recommended | D7: Event | E7: Datetime | F7: End of an activity when duration is available. | G7: Workflow/task completion | H7: Activity duration and waiting-time decomposition. | I7: Supports human-minutes and SLA measurement. | J7: https://learn.microsoft.com/en-us/power-automate/process-mining-processes-and-data
A8: EVT-007 | B8: Source_System | C8: AGI required | D8: Event | E8: String | F8: System emitting the event: Sales Eco, Business Central, Logistics App, bank interface, Fabric-derived, etc. | G8: Integration/source metadata | H8: System-switch and source-reliability analysis. | I8: Evidence provenance. | J8: https://learn.microsoft.com/en-us/dynamics365/business-central/dev-itpro/webservices/web-service-telemetry
A9: EVT-008 | B9: Source_Record_ID | C9: AGI required | D9: Event | E9: String | F9: Native record key from the source system. | G9: Source table/API primary key | H9: Drill-back and reconciliation. | I9: Supports source-record sampling. | J9: https://learn.microsoft.com/en-us/power-automate/process-mining-normalized-import-authoring-guide
A10: EVT-009 | B10: Document_Type | C10: AGI required | D10: Event | E10: String | F10: Customer Order, SO, DO, DN/Shipment, Invoice, MR/Receipt, Return, Credit Memo. | G10: Sales Eco / BC / Logistics metadata | H10: Document-chain analysis. | I10: Supports chain-completeness controls. | J10: https://learn.microsoft.com/en-us/power-automate/process-mining-normalized-import-authoring-guide
A11: EVT-010 | B11: Document_No | C11: AGI required | D11: Event | E11: String | F11: Authoritative document number at the current step. | G11: Source document number | H11: Drill-through and chain linking. | I11: Primary reconciliation evidence. | J11: https://learn.microsoft.com/en-us/power-automate/process-mining-normalized-import-authoring-guide
A12: EVT-011 | B12: Parent_Document_No | C12: AGI required | D12: Event | E12: String | F12: Immediate upstream document number or cross-reference. | G12: CO/SO/DO/DN/Invoice references | H12: Builds parent-child document chain. | I12: Detects orphan documents and broken lineage. | J12: https://learn.microsoft.com/en-us/power-automate/process-mining-normalized-import-authoring-guide
... A34: EVT-033 | B34: Document_Line_ID | C34: Recommended | D34: Event | E34: String | F34: Stable line-level identifier or governed composite key for document-line reconciliation. | G34: Sales Eco line ID / Business Central line ID or line number / Logistics line reference | H34: Line-level chain matching and partial-fulfilment analysis. | I34: Prevents quantity aggregation from hiding line-level mismatches. | J34: https://learn.microsoft.com/en-us/dynamics365/business-central/dev-itpro/api-reference/v2.0/

Sheet O2C Pilot KPI Baseline
A1: KPI ID | B1: Metric ID | C1: Pilot KPI | D1: KPI Family | E1: Calculation | F1: Unit | G1: Required Events / Data | H1: Baseline Period | I1: Baseline Value | J1: Evidence Level | K1: Data Quality Status | L1: Owner | M1: Acceptance Rule | N1: Current Status
A2: KPI-O2C-01 | B2: M-O2C-02 | C2: Digital Order Adoption | D2: Adoption | E2: Digital eligible orders / all eligible orders | F2: % | G2: Order source, eligibility, organization, timestamp | H2: TBD - first production sample | I2: TBD | J2: E2 max until live data | K2: Not assessed | L2: Sales Process Owner + Product/Data | M2: No baseline published until digital and manual eligible populations reconcile. | N2: Ready for extraction design
A3: KPI-O2C-02 | B3: M-O2C-30 | C3: CO→SO Straight-Through Rate | D3: Automation | E3: Eligible COs converted to SO with zero human action events / eligible submitted COs | F3: % | G3: CO submit; human actions; SO create; correlation ID | H3: TBD - first production sample | I3: TBD | J3: E2 max until live data | K3: Not assessed | L3: Sales + ERP/Product | M3: Count integrations/system rules as automated, not human touches; approved exceptions separate. | N3: Ready for extraction design
A4: KPI-O2C-03 | B4: M-O2C-31 | C4: Average CO→SO Cycle Time | D4: Process Performance | E4: Average(SO created - CO accepted/submitted) | F4: Minutes / hours | G4: CO accepted timestamp; SO created timestamp; case/correlation key | H4: TBD - first production sample | I4: TBD | J4: E2 max until live data | K4: Not assessed | L4: Sales + ERP/Product | M4: At least 95% of sampled COs need valid SO link or documented exclusion before publishing. | N4: Ready for extraction design
A5: KPI-O2C-04 | B5: M-O2C-06 | C5: Credit Auto-Clear Rate | D5: Automation / Control | E5: Auto-cleared credit checks / all credit-checked orders | F5: % | G5: Credit check, limit, exposure, result, approval flag | H5: TBD - first production sample | I5: TBD | J5: E2 max until live data | K5: Not assessed | L5: Finance / ICC + ERP | M5: Every denominator case must have explicit check result; silent bypass is a data-quality failure. | N5: Ready for extraction design
A6: KPI-O2C-05 | B6: M-O2C-07 | C6: Credit Exception / Override Rate | D6: Exception / Control | E6: Credit exception or approved override orders / credit-checked orders | F6: % | G6: Credit check result, approval request/decision, override reason | H6: TBD - first production sample | I6: TBD | J6: E2 max until live data | K6: Not assessed | L6: Finance / ICC | M6: Separate approved override, rejection and unauthorized bypass. | N6: Ready for extraction design
A7: KPI-O2C-06 | B7: M-O2C-12 | C7: SO→DO Cycle Time | D7: Process Performance | E7: Average(DO created - SO eligible/approved) | F7: Hours | G7: SO eligibility/approval and DO creation timestamps | H7: TBD - first production sample | I7: TBD | J7: E2 max until live data | K7: Not assessed | L7: Sales / Logistics | M7: Define one SO-ready event and use it consistently across SBUs. | N7: Ready for extraction design
A8: KPI-O2C-07 | B8: M-O2C-32 | C8: Partial Fulfillment Rate | D8: Fulfilment / Exception | E8: Orders with multi-delivery or positive undelivered balance after first delivery / eligible fulfilled orders | F8: % | G8: SO qty, DO/DN qty, delivered qty, outstanding qty, split reason | H8: TBD - first production sample | I8: TBD | J8: E2 max until live data | K8: Not assessed | L8: Sales / Logistics / Inventory | M8: Tag intentional planned splits separately from stock/logistics-driven partials. | N8: Ready for extraction design
A9: KPI-O2C-08 | B9: M-O2C-13 | C9: DO→Dispatch Cycle Time | D9: Process Performance | E9: Average(dispatch - DO ready) | F9: Hours | G9: DO ready, loading, gate and dispatch timestamps | H9: TBD - first production sample | I9: TBD | J9: E1-E2 until live logistics events | K9: Not assessed | L9: Logistics | M9: Missing gate/dispatch timestamps must be reported as coverage gaps, not imputed. | N9: Ready for extraction design
A10: KPI-O2C-09 | B10: M-O2C-18 | C10: POD Capture Rate | D10: Adoption / Control | E10: Completed deliveries with complete required digital POD / completed deliveries | F10: % | G10: Delivery complete; POD evidence; recipient; timestamp; exception | H10: TBD - first production sample | I10: TBD | J10: E1-E2 until live logistics events | K10: Not assessed | L10: Logistics | M10: POD completeness criteria must be defined by SBU/channel before baseline publication. | N10: Ready for extraction design
A11: KPI-O2C-10 | B11: M-O2C-19 | C11: Delivery Exception Rate | D11: Exception | E11: Deliveries with shortage/damage/rejection/partial exception / delivery attempts | F11: % | G11: Delivery attempt, delivered qty, exception code, reason | H11: TBD - first production sample | I11: TBD | J11: E1-E2 until live logistics events | K11: Not assessed | L11: Logistics / Sales | M11: Use governed reason taxonomy; missing reason is not treated as no exception. | N11: Ready for extraction design
A12: KPI-O2C-11 | B12: M-O2C-20 | C12: Delivery→Invoice Cycle Time | D12: Process Performance | E12: Average(invoice posted - eligible delivery confirmation) | F12: Minutes / hours | G12: DN/shipment/POD eligibility and invoice posting timestamps | H12: TBD - first production sample | I12: TBD | J12: E2 max until live posting sample | K12: Not assessed | L12: Finance / Sales | M12: Invoice must reconcile to source delivery and quantity/amount before latency is accepted. | N12: Ready for extraction design
... A16: KPI-O2C-15 | B16: M-O2C-03 | C16: Human Touches per O2C Case | D16: Human Dependency | E16: Distinct human action events / completed O2C cases | F16: Touches / case | G16: Actor, role, execution type, activity, case ID | H16: TBD - first production sample | I16: TBD | J16: E1-E2 until events classified | K16: Not assessed | L16: Process Owner + Product/Data | M16: Exclude passive views/system events; include approvals, corrections, entries, reconciliations and exception actions. | N16: Ready for extraction design

Sheet O2C Jira Evidence
A1: Jira Key | B1: Summary | C1: O2C Segment | D1: Related Process Steps | E1: Current Jira Status | F1: Resolution | G1: Evidence Contribution | H1: Evidence Ceiling | I1: Calibration Interpretation | J1: Jira URL | K1: Reviewed On
A2: BSES-1331 | B2: Dealer onboarding Cash/Credit ICC terms condition rule | C2: Customer onboarding | D2: O2C-001:003 | E2: QA In Review | F2: Open | G2: Confirms active QA of customer-onboarding rule across Primary Sales organizations. | H2: E2 candidate | I2: Supports configured/delivered evidence only; does not prove live adoption or approval performance. | J2: https://anwarenterprisesystem.atlassian.net/browse/BSES-1331 | K2: 2026-09-14
A3: BSES-1336 | B3: ZSM create Customer Order | C3: Order intake | D3: O2C-005 | E3: QA In Review | F3: Open | G3: Confirms Customer Order capability exists in QA flow. | H3: E2 candidate | I3: Cannot be treated as production execution evidence until live CO transactions are sampled. | J3: https://anwarenterprisesystem.atlassian.net/browse/BSES-1336 | K3: 2026-09-14
A4: BSES-1411 | B4: SO add ZSM Customer Order create permission | C4: Order intake / access | D4: O2C-005 | E4: Done | F4: Done | G4: Confirms role-permission implementation work completed. | H4: E2 candidate | I4: Permission delivery supports configured state, not actual usage/adoption. | J4: https://anwarenterprisesystem.atlassian.net/browse/BSES-1411 | K4: 2026-09-14
A5: BSES-1538 | B5: Invoice Tally Sync | C5: Invoice synchronization | D5: O2C-021:022 | E5: QA In Review | F5: Open | G5: Shows invoice integration/synchronization remains under QA. | H5: E2 candidate | I5: Invoice process cannot be promoted beyond E2 without posted invoice and sync evidence. | J5: https://anwarenterprisesystem.atlassian.net/browse/BSES-1538 | K5: 2026-09-14
A6: BSES-1792 | B6: MR bank subbranch sync to Dynamics | C6: Collection / receipt | D6: O2C-023:024 | E6: QA In Review | F6: Open | G6: Confirms MR banking synchronization capability is not yet fully accepted. | H6: E2 candidate | I6: Digital receipt/payment application needs production evidence and reconciliation. | J6: https://anwarenterprisesystem.atlassian.net/browse/BSES-1792 | K6: 2026-09-14
A7: BSES-2719 | B7: Customer Order correction to reverse status to Rejected for AIL | C7: Order exception / status governance | D7: O2C-005 | E7: Done | F7: Done | G7: Confirms implemented status-correction handling for a production-relevant exception. | H7: E2 candidate | I7: Provides exception-control implementation evidence; live frequency/outcome still unknown. | J7: https://anwarenterprisesystem.atlassian.net/browse/BSES-2719 | K7: 2026-09-14
A8: BSES-2761 | B8: Sales Return details API UOM fields | C8: Sales return | D8: O2C-026:027 | E8: Done | F8: Done | G8: Confirms delivered sales-return API enhancement including UOM details. | H8: E2 candidate | I8: Return chain requires live return, inventory and credit memo evidence for E3/E4. | J8: https://anwarenterprisesystem.atlassian.net/browse/BSES-2761 | K8: 2026-09-14
A9: BSES-2923 | B9: Production DO/DN load time optimization | C9: Fulfilment performance | D9: O2C-011:020 | E9: Done | F9: Done | G9: Shows delivery-document performance optimization was completed. | H9: E2 candidate | I9: Need runtime response metrics and actual process cycle metrics; application speed is not process maturity. | J9: https://anwarenterprisesystem.atlassian.net/browse/BSES-2923 | K9: 2026-09-14
A10: BSES-2928 | B10: Display item name and backlog quantity during DO creation | C10: SO→DO / partial fulfilment | D10: O2C-011 | E10: To Do | F10: Open | G10: Confirms a remaining visibility gap around backlog/outstanding quantity during DO creation. | H10: E1 requirement | I10: Important blocker for transparent partial-fulfilment and outstanding-balance management. | J10: https://anwarenterprisesystem.atlassian.net/browse/BSES-2928 | K10: 2026-09-14
A11: BSES-2941 | B11: Optimize DO, DN, MR paginated lists | C11: Fulfilment / collection usability | D11: O2C-011:024 | E11: In Review | F11: Open | G11: Shows performance enhancement is still under review. | H11: E2 candidate | I11: Not process execution proof; may affect adoption if latency remains material. | J11: https://anwarenterprisesystem.atlassian.net/browse/BSES-2941 | K11: 2026-09-14
A12: BSES-3057 | B12: SO & DO optimization, sync fixes and filter fixes | C12: SO→DO / integration reliability | D12: O2C-005,O2C-011 | E12: Done | F12: Done | G12: Strong current evidence that SO/DO optimization and sync fixes have been delivered. | H12: E2 candidate | I12: Promotion to E3 requires production transaction and sync logs after deployment. | J12: https://anwarenterprisesystem.atlassian.net/browse/BSES-3057 | K12: 2026-09-14
... A25: BSES-2987 | B25: Validate Collection dashboard accessibility, performance and business acceptance | C25: Collection acceptance | D25: O2C-025,O2C-029 | E25: To Do | F25: Open | G25: Business acceptance/performance testing is pending. | H25: E1 requirement | I25: Management layer cannot be considered adopted until this is evidenced. | J25: https://anwarenterprisesystem.atlassian.net/browse/BSES-2987 | K25: 2026-09-14

Sheet O2C Evidence Collection Plan
A1: Pack ID | B1: Evidence Pack | C1: Primary Owner | D1: Source System | E1: Scope / Required Extract | F1: Preferred Window | G1: Join / Key Requirement | H1: Primary KPIs Enabled | I1: Validation Test | J1: Minimum Acceptance | K1: Evidence Level Supported | L1: Priority | M1: Status
A2: COL-O2C-01 | B2: Customer Order event extract | C2: Sales Product / Data | D2: Sales Eco | E2: Customer Order header/lines plus create, submit, approve/reject/correct/cancel status history and actor timestamps. | F2: Last 30-60 days | G2: CO ID; organization; customer; user; RC; correlation/external ID | H2: Digital Order Adoption; CO→SO STP; CO→SO Cycle; Human Touches | I2: Reconcile order counts to application totals and sample 20 cases back to UI/source records. | J2: ≥98% event rows have CO ID and timestamp; ≥95% eligible COs carry usable downstream linkage or documented exclusion. | K2: E3-E4 | L2: P0 | M2: Ready to request
A3: COL-O2C-02 | B3: Sales Eco→BC integration telemetry | C3: ERP Integration / Engineering | D3: Integration service + Business Central telemetry | E3: Request/response logs for customer, CO/SO and other O2C APIs including endpoint, correlation/client-request-id, HTTP result, retry and elapsed time. | F3: Last 30-60 days | G3: Correlation_ID / client-request-id mapped to CO/customer/SO where available | H3: CO→SO STP; integration failure rate; cycle time | I3: Compare integration call counts with source requests and BC-created records. | J3: No unexplained success/failure gap above 2%; retries and failures traceable to source case. | K3: E3-E4 | L3: P0 | M3: Ready to request
A4: COL-O2C-03 | B4: BC Sales Order / Delivery / Invoice chain | C4: ERP / Finance | D4: Business Central | E4: Sales Order, shipment/DN, posted invoice and related ledger references with document numbers, dates, customer, RC, quantities, amounts, statuses and source references. | F4: Last 30-60 days | G4: SO No.; source CO/external ID; shipment/DN ref; invoice No.; customer; RC | H4: CO→SO Cycle; SO→DO/dispatch; Delivery→Invoice; chain reconciliation | I4: Select 30 completed cases and trace each upstream/downstream document and amount/quantity conservation. | J4: ≥95% sampled completed cases reconstructable without manual guesswork; all exceptions explicitly classified. | K4: E3-E4 | L4: P0 | M4: Ready to request
A5: COL-O2C-04 | B5: Credit check & approval evidence | C5: Finance / ICC | D5: Business Central / approval workflow | E5: Credit limit/exposure snapshot, check result, exception flag, approval request/decision, approver and timestamps per order. | F5: Last 30-60 days | G5: SO/CO No.; customer; RC; approval entry ID | H5: Credit Auto-Clear; Credit Exception; Credit Approval Cycle | I5: Sample passed, failed and overridden cases against policy and authority matrix. | J5: Every sampled order has an explicit check outcome or documented policy exclusion; overrides are attributable. | K5: E3-E4 | L5: P0 | M5: Ready to request
A6: COL-O2C-05 | B6: Inventory availability & reservation extract | C6: Inventory / ERP | D6: Business Central | E6: Availability check inputs/results, reservation entries, release events, location/bin, item, quantity and order reference. | F6: Last 30-60 days | G6: SO/DO line; item; location; reservation entry | H6: Stock Availability Pass; Reservation Automation; Partial Fulfillment | I6: Trace shortages and reservation changes to actual inventory ledger and order balances. | J6: ≥95% sampled reserved lines trace to valid SO/DO and inventory location; orphan reservations flagged. | K6: E3-E4 | L6: P1 | M6: Ready to request
A7: COL-O2C-06 | B7: Logistics planning / DO extract | C7: Logistics Product / Operations | D7: Logistics App + BC references | E7: DO creation, source selection, trip grouping, vehicle/driver assignment, loading advice and readiness events. | F7: Last 30-60 days | G7: DO No.; SO No.; trip ID; source location; vehicle ID | H7: SO→DO Cycle; Partial Fulfillment; Human Touches | I7: Reconcile planned DO quantities to SO remaining quantity and actual loading/dispatch. | J7: No DO exceeds authorized outstanding quantity; parent SO reference present for ≥98% of eligible DOs. | K7: E3-E4 | L7: P0 | M7: Ready to request
A8: COL-O2C-07 | B8: Loading / gate / dispatch event extract | C8: Logistics / Warehouse | D8: Logistics App / gate / weighbridge | E8: Loading start/complete, loaded quantity, discrepancy, gate-in/out, dispatch status, vehicle and user/device timestamps. | F8: Last 30-60 days | G8: Trip ID; DO No.; vehicle ID | H8: DO→Dispatch Cycle; Gate Dwell; Dispatch On-Time; Loading Accuracy | I8: Cross-check sample events with gate register/weighbridge/physical dispatch evidence where available. | J8: Timestamp coverage ≥90% for pilot scope before publishing cycle-time metrics; missing events shown explicitly. | K8: E3-E4 | L8: P0 | M8: Ready to request
A9: COL-O2C-08 | B9: POD & delivery exception extract | C9: Logistics | D9: Logistics App | E9: Delivery attempt, delivered quantity, POD recipient/evidence/time, partial/shortage/damage/rejection exception and follow-up action. | F9: Last 30-60 days | G9: Trip ID; DO/DN No.; customer; delivery attempt ID | H9: POD Capture; Delivery Exception; OTIF/partial fulfillment | I9: Sample POD records against actual delivered quantity and exception actions. | J9: POD completeness rules agreed; missing proof and missing exception reason visible rather than excluded. | K9: E3-E4 | L9: P0 | M9: Ready to request
A10: COL-O2C-09 | B10: Money Receipt / bank / payment application extract | C10: Finance / Collection | D10: Sales Eco MR + Business Central | E10: MR/receipt creation, bank/subbranch, BC posting, customer ledger application, invoice link, unapplied amount and correction/reversal events. | F10: Last 30-60 days | G10: MR/receipt No.; customer; bank ref; BC entry; invoice/open entry | H10: Digital Receipt; Payment Auto-Application; DSO/Overdue support | I10: Reconcile receipt counts/amounts to BC customer ledger and sampled bank references. | J10: 100% sampled MR amount traceable to authoritative BC posting or explicit pending/error state. | K10: E3-E4 | L10: P0 | M10: Ready to request
A11: COL-O2C-10 | B11: AR aging / collection / NOD baseline | C11: Finance / Collection | D11: Business Central + existing collection sources | E11: Open AR by due date/aging bucket, customer, RC, collection action/NOD if available, payment linkage and status. | F11: Current month + prior 3 months | G11: Customer; invoice; ledger entry; NOD/commitment ID if available | H11: DSO; Overdue Ratio; recovery baseline | I11: Reconcile open AR total to authoritative finance ledger and document any timing exclusions. | J11: Finance owner signs off AR control total before collection KPIs are published. | K11: E3-E4 | L11: P0 | M11: Ready to request
A12: COL-O2C-11 | B12: Sales return chain extract | C12: Sales / Logistics / Finance | D12: Sales Eco + Business Central | E12: Return request, source DN/invoice, reason, approval, return receipt/inspection, inventory effect, credit memo and timestamps. | F12: Last 60-90 days | G12: Return No.; DN/invoice No.; customer; item/qty | H12: Sales Return Rate; Return-to-Adjustment Cycle | I12: Trace every sampled return quantity through inventory and financial adjustment. | J12: No sampled approved return has unexplained quantity or credit mismatch. | K12: E3-E4 | L12: P1 | M12: Ready to request
... A14: COL-O2C-13 | B14: Canonical O2C event-log build | C14: Data / Fabric | D14: Fabric / OneLake / process intelligence | E14: Build unified event table using O2C Event Schema and normalize document/organization/RC/customer keys. | F14: Pilot 30-60 day window then rolling refresh | G14: Case_ID; Activity_Name; Event_Timestamp; source/document/correlation keys | H14: All 15 pilot KPIs; variants; bottlenecks; exceptions | I14: Coverage, duplicate, orphan, chronology and quantity/amount conservation tests before metric certification. | J14: Core required fields ≥98% complete for pilot cases; known gaps quantified and not silently imputed. | K14: E4 | L14: P0 | M14: Blocked until source extracts obtained

Sheet O2C Source-to-Field Mapping
A1: Mapping ID | B1: Event Field | C1: Source Domain / System | D1: Source Object / API / Log Candidate | E1: Source Field / Attribute Candidate | F1: Mapping Status | G1: Evidence Basis | H1: Derivation / Fallback Rule | I1: Join Key | J1: Data Quality Check | K1: Process Scope | L1: Technical Owner | M1: Business Owner | N1: Validation Action | O1: Notes
A2: MAP-O2C-001 | B2: Case_ID | C2: Fabric / Cross-system | D2: Canonical O2C event-log transform | E2: Derived from governed CO/SO chain key; use native shared external/reference ID if one exists | F2: Derived - needs technical validation | G2: Sales Eco docs require external/BC references, correlation and reconciliation; Process Mining requires Case ID. | H2: Prefer Sales Eco Customer Order/external ID when it survives downstream; otherwise build a cross-reference bridge CO↔SO↔DO↔DN↔Invoice↔Receipt/Return. | I2: CO external/ref ID + BC SO No./GUID + downstream references | J2: 100% event rows in pilot must resolve to one case or explicit orphan category; no case key reused across unrelated orders. | K2: All O2C | L2: Data/Fabric + ERP Integration | M2: Sales Process Owner + Finance | N2: Trace 30 completed cases manually and prove one-to-one/one-to-many lineage before freezing Case_ID rule. | O2: Do not use customer ID alone as case ID.
A3: MAP-O2C-002 | B3: Event_ID | C3: All source systems | D3: Native audit/event row or ingestion-generated event key | E3: Native event/audit ID where available | F3: Candidate | G3: Required by AGI evidence model for deduplication and source trace. | H3: If source has no event ID, hash Source_System + Source_Record_ID + Activity_Name + Event_Timestamp + sequence discriminator. | I3: Source record + event timestamp + action | J3: Event_ID unique; zero duplicates after normalized retry handling. | K3: All O2C | L3: Data/Fabric | M3: Transformation Office | N3: Profile duplicate event keys and compare to source counts. | O3: Retries should remain separate technical events only when analytically required.
A4: MAP-O2C-003 | B4: Activity_Name | C4: Sales Eco / BC / Logistics / Finance | D4: Audit action, workflow status change, posting event, logistics event | E4: Action/status/event name | F4: Candidate - normalization required | G4: Sales Eco requires create/update/submit/approve/reject/resubmit audit; Microsoft Process Mining requires Activity Name. | H4: Map source-specific actions to controlled enterprise labels such as CO Submitted, SO Created, Credit Approved, DO Created, Dispatched, POD Captured, Invoice Posted, Payment Applied. | I4: Source event/action code | J4: No free-text activity names in certified dataset; unmapped actions quarantined. | K4: All O2C | L4: Data/Fabric + Product | M4: Process Owner | N4: Approve activity dictionary with Sales, Logistics and Finance owners. | O4: Keep raw source action in a separate lineage field if available.
A5: MAP-O2C-004 | B5: Event_Timestamp | C5: All source systems | D5: Audit/workflow/posting/gate/POD/integration event | E5: Created/updated/approved/posted/event timestamp | F5: Candidate | G5: Sales Eco audit requires timestamp; Process Mining requires timestamp. | H5: Use business-event timestamp, not ingestion timestamp. Store ingestion time separately if needed. | I5: Source_Record_ID / Event_ID | J5: Timestamp non-null for core milestones; chronology anomalies flagged, not silently corrected. | K5: All O2C | L5: Source system owners + Data | M5: Compare source UI/audit timestamps against extract for sampled cases and confirm timezone. | N5: Normalize to UTC plus retain local offset or Dhaka-local business date.
A6: MAP-O2C-005 | B6: Start_Timestamp | C6: Workflow-capable systems | D6: Approval/task/work item history | E6: Task/workflow start or assignment timestamp | F6: Candidate / may be unavailable | G6: Microsoft Process Mining supports start/end timestamps for activity duration. | H6: Where only point events exist, leave null; do not infer active work duration from prior event. | I6: Workflow/task ID | J6: Start <= End; coverage reported by activity. | K6: Approvals / human tasks | L6: Product/ERP/Logistics owners | M6: Process Owner | N6: Identify which workflows expose assignment/start events. | O6: Optional for point events.
A7: MAP-O2C-006 | B7: End_Timestamp | C7: Workflow-capable systems | D7: Approval/task/work item history | E7: Decision/completion timestamp | F7: Candidate / may be unavailable | G7: Microsoft Process Mining supports start/end timestamps. | H7: Use actual completion/decision time. Leave null if event is instantaneous. | I7: Workflow/task ID | J7: End >= Start; completion coverage reported. | K7: Approvals / human tasks | L7: Product/ERP/Logistics owners | M7: Process Owner | N7: Validate against workflow history for sample tasks. | O7: Needed for active-time measurement, not basic event sequencing.
A8: MAP-O2C-007 | B8: Source_System | C8: Ingestion layer | D8: Source connection metadata | E8: SalesEco / BusinessCentral / Logistics / Bank / FabricDerived | F8: Confirmed-derived | G8: Source provenance is required by the enterprise evidence model. | H8: Stamp at ingestion; do not accept user-entered source labels. | I8: Pipeline/source connection | J8: Value restricted to governed source-system dimension. | K8: All O2C | L8: Data/Fabric | M8: Transformation Office | N8: Freeze source-system code list before pilot load. | O8: Separate source from business function.
A9: MAP-O2C-008 | B9: Source_Record_ID | C9: Sales Eco / BC / Logistics | D9: Native entity or ledger/API record | E9: Native GUID/ID/entry number | F9: Candidate | G9: Sales Eco documentation requires record ID in audit/support context; BC APIs expose GUID IDs. | H9: Use immutable native key, not display name. | I9: Native ID | J9: Non-null for extracted source records; uniqueness checked within source object. | K9: All O2C | L9: Application/ERP owners | M9: Data Owner | N9: Confirm stable primary key per source object/API. | O9: Display document number remains separate.
A10: MAP-O2C-009 | B10: Document_Type | C10: Sales Eco / BC / Logistics / Finance | D10: Entity/document metadata | E10: CO / Sales Order / DO / Shipment-DN / Invoice / MR-Receipt / Return / Credit Memo | F10: Confirmed concept; normalization required | G10: Sales Eco baseline explicitly defines the O2C document chain. | H10: Map source entity/object to governed document-type dimension. | I10: Source object/entity type | J10: All events with document context have a valid controlled type. | K10: Transactional O2C | L10: Data/Fabric + Product | M10: Sales + Finance | N10: Approve canonical type list and synonyms. | O10: Do not conflate DN with DO; BC mapping for DN may use posted sales shipment.
A11: MAP-O2C-010 | B11: Document_No | C11: Sales Eco / Business Central / Logistics | D11: CO/DO/MR entity; BC salesOrder, salesShipment, salesInvoice or custom APIs | E11: Sales Eco number/reference; BC number; Logistics DO/DN/trip reference | F11: Candidate | G11: BC API v2.0 exposes number on sales orders/shipments/invoices; Sales Eco requires record/document references. | H11: Use authoritative displayed document number for business reconciliation; retain Source_Record_ID for technical joins. | I11: Native source record ID | J11: Uniqueness by Document_Type + Organization; duplicates investigated. | K11: Transactional O2C | L11: Application/ERP/Logistics | M11: Sales / Logistics / Finance | N11: Confirm document-number fields in production APIs/extensions. | O11: BC standard resources verified for Sales Order, Sales Shipment and Sales Invoice.
A12: MAP-O2C-011 | B12: Parent_Document_No | C12: Sales Eco / BC / Logistics | D12: Cross-reference/source document fields | E12: Source CO/SO/DO/DN/Invoice reference; BC orderNumber/externalDocumentNumber where applicable | F12: Candidate - technical validation required | G12: Sales Eco requires line-by-line reconciliation and BC document references; BC salesShipment exposes orderNumber. | H12: Use immediate authoritative parent reference; build a bridge table when no single parent field exists. | I12: Document_No + source reference | J12: Orphan child documents explicitly flagged; no fuzzy matching for certified lineage. | K12: SO→DO→DN→Invoice→Receipt/Return | L12: ERP Integration + Data | M12: Finance + Sales | N12: Validate 30 chains and document which parent fields survive each transition. | O12: One SO can legitimately have multiple downstream delivery documents.
A13: MAP-O2C-012 | B13: Correlation_ID | C13: Sales Eco integration / Business Central telemetry | D13: Integration log + BC web-service telemetry | E13: Sales Eco correlation/reference ID; client-request-id / OperationId where configured | F13: Confirmed requirement; deployment mapping to validate | G13: Sales Eco baseline explicitly requires correlation ID/retry count; BC telemetry supports client-request-id correlation. | H13: Propagate the same request correlation identifier across caller and BC where technically possible. | I13: Integration request ID | J13: Coverage of correlation ID reported for all integration-driven events; duplicate IDs across unrelated requests prohibited. | K13: Integration-driven O2C | L13: ERP Integration / Engineering | M13: Product + Support | N13: Inspect deployed integration headers/log schema and confirm correlation propagation. | O13: Critical for safe retry and root-cause analysis.
A14: MAP-O2C-013 | B14: Organization | C14: Sales Eco / Business Central | D14: Sales Eco organization + BC company context | E14: Organization ID/code; BC company ID/name | F14: Confirmed concept; mapping table required | G14: Sales Eco states organization is primary isolation boundary; BC API calls are company-scoped. | H14: Maintain governed Organization↔BC Company bridge. | I14: Organization ID / company GUID | J14: Every case maps to exactly one organization; cross-org references are errors unless explicitly approved. | K14: All O2C | L14: Product Master Data + ERP | M14: Org Admin / Finance | N14: Validate organization-company mapping against production configuration. | O14: Use IDs/codes, not display names, as keys.
A15: MAP-O2C-014 | B15: Responsibility_Center | C15: Sales Eco / Business Central | D15: Order/integration payload + BC custom field/dimension/extension candidate | E15: RC code / Responsibility Center value | F15: Needs technical validation | G15: Project decisions require CO/DO submission context and RC-based credit/inventory; exact production storage may be custom. | H15: Prefer actual persisted BC transaction field or governed dimension; do not infer from user when transaction carries explicit RC. | I15: CO/SO/DO reference + RC code | J15: RC must belong to same organization; missing RC separated from intentionally optional RC. | K15: Order / credit / inventory / finance | L15: ERP Extension + Product | M15: Sales + Finance | N15: Inspect BC extension/API payload and production storage; freeze mapping only after field confirmation. | O15: Do not assume standard API v2.0 exposes custom RC directly.
